{".class":"MypyFile","_fullname":"google.cloud.aiplatform_v1beta1.services.feature_registry_service.pagers","future_import_flags":[],"is_partial_stub_package":false,"is_stub":false,"names":{".class":"SymbolTable","Any":{".class":"SymbolTableNode","cross_ref":"typing.Any","kind":"Gdef"},"AsyncIterator":{".class":"SymbolTableNode","cross_ref":"typing.AsyncIterator","kind":"Gdef"},"Awaitable":{".class":"SymbolTableNode","cross_ref":"typing.Awaitable","kind":"Gdef"},"Callable":{".class":"SymbolTableNode","cross_ref":"typing.Callable","kind":"Gdef"},"Iterator":{".class":"SymbolTableNode","cross_ref":"typing.Iterator","kind":"Gdef"},"ListFeatureGroupsAsyncPager":{".class":"SymbolTableNode","kind":"Gdef","node":{".class":"TypeInfo","_promote":[],"abstract_attributes":[],"alt_promote":null,"bases":["builtins.object"],"dataclass_transform_spec":null,"declared_metaclass":null,"defn":{".class":"ClassDef","fullname":"google.cloud.aiplatform_v1beta1.services.feature_registry_service.pagers.ListFeatureGroupsAsyncPager","name":"ListFeatureGroupsAsyncPager","type_vars":[]},"deletable_attributes":[],"deprecated":null,"flags":[],"fullname":"google.cloud.aiplatform_v1beta1.services.feature_registry_service.pagers.ListFeatureGroupsAsyncPager","has_param_spec_type":false,"metaclass_type":null,"metadata":{},"module_name":"google.cloud.aiplatform_v1beta1.services.feature_registry_service.pagers","mro":["google.cloud.aiplatform_v1beta1.services.feature_registry_service.pagers.ListFeatureGroupsAsyncPager","builtins.object"],"names":{".class":"SymbolTable","__aiter__":{".class":"SymbolTableNode","kind":"Mdef","node":{".class":"FuncDef","abstract_status":0,"arg_kinds":[0],"arg_names":["self"],"dataclass_transform_spec":null,"deprecated":null,"flags":["is_trivial_self"],"fullname":"google.cloud.aiplatform_v1beta1.services.feature_registry_service.pagers.ListFeatureGroupsAsyncPager.__aiter__","name":"__aiter__","original_first_arg":"self","type":{".class":"CallableType","arg_kinds":[0],"arg_names":["self"],"arg_types":["google.cloud.aiplatform_v1beta1.services.feature_registry_service.pagers.ListFeatureGroupsAsyncPager"],"fallback":"builtins.function","from_concatenate":false,"implicit":false,"imprecise_arg_kinds":false,"is_bound":false,"is_ellipsis_args":false,"name":"__aiter__ of ListFeatureGroupsAsyncPager","ret_type":{".class":"Instance","args":["google.cloud.aiplatform_v1beta1.types.feature_group.FeatureGroup"],"extra_attrs":null,"type_ref":"typing.AsyncIterator"},"type_guard":null,"type_is":null,"unpack_kwargs":false,"variables":[]}}},"__getattr__":{".class":"SymbolTableNode","kind":"Mdef","node":{".class":"FuncDef","abstract_status":0,"arg_kinds":[0,0],"arg_names":[null,null],"dataclass_transform_spec":null,"deprecated":null,"flags":["is_trivial_self"],"fullname":"google.cloud.aiplatform_v1beta1.services.feature_registry_service.pagers.ListFeatureGroupsAsyncPager.__getattr__","name":"__getattr__","original_first_arg":"self","type":{".class":"CallableType","arg_kinds":[0,0],"arg_names":[null,null],"arg_types":["google.cloud.aiplatform_v1beta1.services.feature_registry_service.pagers.ListFeatureGroupsAsyncPager","builtins.str"],"fallback":"builtins.function","from_concatenate":false,"implicit":false,"imprecise_arg_kinds":false,"is_bound":false,"is_ellipsis_args":false,"name":"__getattr__ of ListFeatureGroupsAsyncPager","ret_type":{".class":"AnyType","missing_import_name":null,"source_any":null,"type_of_any":2},"type_guard":null,"type_is":null,"unpack_kwargs":false,"variables":[]}}},"__init__":{".class":"SymbolTableNode","kind":"Mdef","node":{".class":"FuncDef","abstract_status":0,"arg_kinds":[0,0,0,0,5,5,5],"arg_names":["self","method","request","response","retry","timeout","metadata"],"dataclass_transform_spec":null,"deprecated":null,"flags":["is_trivial_self"],"fullname":"google.cloud.aiplatform_v1beta1.services.feature_registry_service.pagers.ListFeatureGroupsAsyncPager.__init__","name":"__init__","original_first_arg":"self","type":{".class":"CallableType","arg_kinds":[0,0,0,0,5,5,5],"arg_names":["self","method","request","response","retry","timeout","metadata"],"arg_types":["google.cloud.aiplatform_v1beta1.services.feature_registry_service.pagers.ListFeatureGroupsAsyncPager",{".class":"CallableType","arg_kinds":[2,4],"arg_names":[null,null],"arg_types":[{".class":"AnyType","missing_import_name":null,"source_any":null,"type_of_any":2},{".class":"AnyType","missing_import_name":null,"source_any":null,"type_of_any":2}],"fallback":"builtins.function","from_concatenate":false,"implicit":false,"imprecise_arg_kinds":false,"is_bound":false,"is_ellipsis_args":true,"name":null,"ret_type":{".class":"Instance","args":["google.cloud.aiplatform_v1beta1.types.feature_registry_service.ListFeatureGroupsResponse"],"extra_attrs":null,"type_ref":"typing.Awaitable"},"type_guard":null,"type_is":null,"unpack_kwargs":false,"variables":[]},"google.cloud.aiplatform_v1beta1.types.feature_registry_service.ListFeatureGroupsRequest","google.cloud.aiplatform_v1beta1.types.feature_registry_service.ListFeatureGroupsResponse",{".class":"TypeAliasType","args":[],"type_ref":"google.cloud.aiplatform_v1beta1.services.feature_registry_service.pagers.OptionalAsyncRetry"},{".class":"UnionType","items":["builtins.float","builtins.object"],"uses_pep604_syntax":false},{".class":"Instance","args":[{".class":"TupleType","implicit":false,"items":["builtins.str",{".class":"UnionType","items":["builtins.str","builtins.bytes"],"uses_pep604_syntax":false}],"partial_fallback":{".class":"Instance","args":[{".class":"AnyType","missing_import_name":null,"source_any":null,"type_of_any":6}],"extra_attrs":null,"type_ref":"builtins.tuple"}}],"extra_attrs":null,"type_ref":"typing.Sequence"}],"fallback":"builtins.function","from_concatenate":false,"implicit":false,"imprecise_arg_kinds":false,"is_bound":false,"is_ellipsis_args":false,"name":"__init__ of ListFeatureGroupsAsyncPager","ret_type":{".class":"NoneType"},"type_guard":null,"type_is":null,"unpack_kwargs":false,"variables":[]}}},"__repr__":{".class":"SymbolTableNode","kind":"Mdef","node":{".class":"FuncDef","abstract_status":0,"arg_kinds":[0],"arg_names":[null],"dataclass_transform_spec":null,"deprecated":null,"flags":["is_trivial_self"],"fullname":"google.cloud.aiplatform_v1beta1.services.feature_registry_service.pagers.ListFeatureGroupsAsyncPager.__repr__","name":"__repr__","original_first_arg":"self","type":{".class":"CallableType","arg_kinds":[0],"arg_names":[null],"arg_types":["google.cloud.aiplatform_v1beta1.services.feature_registry_service.pagers.ListFeatureGroupsAsyncPager"],"fallback":"builtins.function","from_concatenate":false,"implicit":false,"imprecise_arg_kinds":false,"is_bound":false,"is_ellipsis_args":false,"name":"__repr__ of ListFeatureGroupsAsyncPager","ret_type":"builtins.str","type_guard":null,"type_is":null,"unpack_kwargs":false,"variables":[]}}},"_metadata":{".class":"SymbolTableNode","implicit":true,"kind":"Mdef","node":{".class":"Var","flags":["is_ready","is_inferred"],"fullname":"google.cloud.aiplatform_v1beta1.services.feature_registry_service.pagers.ListFeatureGroupsAsyncPager._metadata","name":"_metadata","setter_type":null,"type":{".class":"Instance","args":[{".class":"TupleType","implicit":false,"items":["builtins.str",{".class":"UnionType","items":["builtins.str","builtins.bytes"],"uses_pep604_syntax":false}],"partial_fallback":{".class":"Instance","args":[{".class":"AnyType","missing_import_name":null,"source_any":null,"type_of_any":6}],"extra_attrs":null,"type_ref":"builtins.tuple"}}],"extra_attrs":null,"type_ref":"typing.Sequence"}}},"_method":{".class":"SymbolTableNode","implicit":true,"kind":"Mdef","node":{".class":"Var","flags":["is_ready","is_inferred"],"fullname":"google.cloud.aiplatform_v1beta1.services.feature_registry_service.pagers.ListFeatureGroupsAsyncPager._method","name":"_method","setter_type":null,"type":{".class":"CallableType","arg_kinds":[2,4],"arg_names":[null,null],"arg_types":[{".class":"AnyType","missing_import_name":null,"source_any":null,"type_of_any":2},{".class":"AnyType","missing_import_name":null,"source_any":null,"type_of_any":2}],"fallback":"builtins.function","from_concatenate":false,"implicit":false,"imprecise_arg_kinds":false,"is_bound":false,"is_ellipsis_args":true,"name":null,"ret_type":{".class":"Instance","args":["google.cloud.aiplatform_v1beta1.types.feature_registry_service.ListFeatureGroupsResponse"],"extra_attrs":null,"type_ref":"typing.Awaitable"},"type_guard":null,"type_is":null,"unpack_kwargs":false,"variables":[]}}},"_request":{".class":"SymbolTableNode","implicit":true,"kind":"Mdef","node":{".class":"Var","flags":["is_ready","is_inferred"],"fullname":"google.cloud.aiplatform_v1beta1.services.feature_registry_service.pagers.ListFeatureGroupsAsyncPager._request","name":"_request","setter_type":null,"type":"google.cloud.aiplatform_v1beta1.types.feature_registry_service.ListFeatureGroupsRequest"}},"_response":{".class":"SymbolTableNode","implicit":true,"kind":"Mdef","node":{".class":"Var","flags":["is_ready","is_inferred"],"fullname":"google.cloud.aiplatform_v1beta1.services.feature_registry_service.pagers.ListFeatureGroupsAsyncPager._response","name":"_response","setter_type":null,"type":"google.cloud.aiplatform_v1beta1.types.feature_registry_service.ListFeatureGroupsResponse"}},"_retry":{".class":"SymbolTableNode","implicit":true,"kind":"Mdef","node":{".class":"Var","flags":["is_ready","is_inferred"],"fullname":"google.cloud.aiplatform_v1beta1.services.feature_registry_service.pagers.ListFeatureGroupsAsyncPager._retry","name":"_retry","setter_type":null,"type":{".class":"TypeAliasType","args":[],"type_ref":"google.cloud.aiplatform_v1beta1.services.feature_registry_service.pagers.OptionalAsyncRetry"}}},"_timeout":{".class":"SymbolTableNode","implicit":true,"kind":"Mdef","node":{".class":"Var","flags":["is_ready","is_inferred"],"fullname":"google.cloud.aiplatform_v1beta1.services.feature_registry_service.pagers.ListFeatureGroupsAsyncPager._timeout","name":"_timeout","setter_type":null,"type":{".class":"UnionType","items":["builtins.float","builtins.object"],"uses_pep604_syntax":false}}},"pages":{".class":"SymbolTableNode","kind":"Mdef","node":{".class":"Decorator","func":{".class":"FuncDef","abstract_status":0,"arg_kinds":[0],"arg_names":["self"],"dataclass_transform_spec":null,"deprecated":null,"flags":["is_property","is_generator","is_coroutine","is_async_generator","is_decorated","is_trivial_self"],"fullname":"google.cloud.aiplatform_v1beta1.services.feature_registry_service.pagers.ListFeatureGroupsAsyncPager.pages","name":"pages","original_first_arg":"self","type":{".class":"CallableType","arg_kinds":[0],"arg_names":["self"],"arg_types":["google.cloud.aiplatform_v1beta1.services.feature_registry_service.pagers.ListFeatureGroupsAsyncPager"],"fallback":"builtins.function","from_concatenate":false,"implicit":false,"imprecise_arg_kinds":false,"is_bound":false,"is_ellipsis_args":false,"name":"pages of ListFeatureGroupsAsyncPager","ret_type":{".class":"Instance","args":["google.cloud.aiplatform_v1beta1.types.feature_registry_service.ListFeatureGroupsResponse"],"extra_attrs":null,"type_ref":"typing.AsyncIterator"},"type_guard":null,"type_is":null,"unpack_kwargs":false,"variables":[]}},"is_overload":false,"var":{".class":"Var","flags":["is_initialized_in_class","is_property","is_ready","is_inferred"],"fullname":"google.cloud.aiplatform_v1beta1.services.feature_registry_service.pagers.ListFeatureGroupsAsyncPager.pages","name":"pages","setter_type":null,"type":{".class":"CallableType","arg_kinds":[0],"arg_names":["self"],"arg_types":["google.cloud.aiplatform_v1beta1.services.feature_registry_service.pagers.ListFeatureGroupsAsyncPager"],"fallback":"builtins.function","from_concatenate":false,"implicit":false,"imprecise_arg_kinds":false,"is_bound":false,"is_ellipsis_args":false,"name":"pages of ListFeatureGroupsAsyncPager","ret_type":{".class":"Instance","args":["google.cloud.aiplatform_v1beta1.types.feature_registry_service.ListFeatureGroupsResponse"],"extra_attrs":null,"type_ref":"typing.AsyncIterator"},"type_guard":null,"type_is":null,"unpack_kwargs":false,"variables":[]}}}}},"self_type":{".class":"TypeVarType","default":{".class":"AnyType","missing_import_name":null,"source_any":null,"type_of_any":4},"fullname":"google.cloud.aiplatform_v1beta1.services.feature_registry_service.pagers.ListFeatureGroupsAsyncPager.Self","id":0,"name":"Self","namespace":"","upper_bound":"google.cloud.aiplatform_v1beta1.services.feature_registry_service.pagers.ListFeatureGroupsAsyncPager","values":[],"variance":0},"slots":null,"tuple_type":null,"type_vars":[],"typeddict_type":null}},"ListFeatureGroupsPager":{".class":"SymbolTableNode","kind":"Gdef","node":{".class":"TypeInfo","_promote":[],"abstract_attributes":[],"alt_promote":null,"bases":["builtins.object"],"dataclass_transform_spec":null,"declared_metaclass":null,"defn":{".class":"ClassDef","fullname":"google.cloud.aiplatform_v1beta1.services.feature_registry_service.pagers.ListFeatureGroupsPager","name":"ListFeatureGroupsPager","type_vars":[]},"deletable_attributes":[],"deprecated":null,"flags":[],"fullname":"google.cloud.aiplatform_v1beta1.services.feature_registry_service.pagers.ListFeatureGroupsPager","has_param_spec_type":false,"metaclass_type":null,"metadata":{},"module_name":"google.cloud.aiplatform_v1beta1.services.feature_registry_service.pagers","mro":["google.cloud.aiplatform_v1beta1.services.feature_registry_service.pagers.ListFeatureGroupsPager","builtins.object"],"names":{".class":"SymbolTable","__getattr__":{".class":"SymbolTableNode","kind":"Mdef","node":{".class":"FuncDef","abstract_status":0,"arg_kinds":[0,0],"arg_names":[null,null],"dataclass_transform_spec":null,"deprecated":null,"flags":["is_trivial_self"],"fullname":"google.cloud.aiplatform_v1beta1.services.feature_registry_service.pagers.ListFeatureGroupsPager.__getattr__","name":"__getattr__","original_first_arg":"self","type":{".class":"CallableType","arg_kinds":[0,0],"arg_names":[null,null],"arg_types":["google.cloud.aiplatform_v1beta1.services.feature_registry_service.pagers.ListFeatureGroupsPager","builtins.str"],"fallback":"builtins.function","from_concatenate":false,"implicit":false,"imprecise_arg_kinds":false,"is_bound":false,"is_ellipsis_args":false,"name":"__getattr__ of ListFeatureGroupsPager","ret_type":{".class":"AnyType","missing_import_name":null,"source_any":null,"type_of_any":2},"type_guard":null,"type_is":null,"unpack_kwargs":false,"variables":[]}}},"__init__":{".class":"SymbolTableNode","kind":"Mdef","node":{".class":"FuncDef","abstract_status":0,"arg_kinds":[0,0,0,0,5,5,5],"arg_names":["self","method","request","response","retry","timeout","metadata"],"dataclass_transform_spec":null,"deprecated":null,"flags":["is_trivial_self"],"fullname":"google.cloud.aiplatform_v1beta1.services.feature_registry_service.pagers.ListFeatureGroupsPager.__init__","name":"__init__","original_first_arg":"self","type":{".class":"CallableType","arg_kinds":[0,0,0,0,5,5,5],"arg_names":["self","method","request","response","retry","timeout","metadata"],"arg_types":["google.cloud.aiplatform_v1beta1.services.feature_registry_service.pagers.ListFeatureGroupsPager",{".class":"CallableType","arg_kinds":[2,4],"arg_names":[null,null],"arg_types":[{".class":"AnyType","missing_import_name":null,"source_any":null,"type_of_any":2},{".class":"AnyType","missing_import_name":null,"source_any":null,"type_of_any":2}],"fallback":"builtins.function","from_concatenate":false,"implicit":false,"imprecise_arg_kinds":false,"is_bound":false,"is_ellipsis_args":true,"name":null,"ret_type":"google.cloud.aiplatform_v1beta1.types.feature_registry_service.ListFeatureGroupsResponse","type_guard":null,"type_is":null,"unpack_kwargs":false,"variables":[]},"google.cloud.aiplatform_v1beta1.types.feature_registry_service.ListFeatureGroupsRequest","google.cloud.aiplatform_v1beta1.types.feature_registry_service.ListFeatureGroupsResponse",{".class":"TypeAliasType","args":[],"type_ref":"google.cloud.aiplatform_v1beta1.services.feature_registry_service.pagers.OptionalRetry"},{".class":"UnionType","items":["builtins.float","builtins.object"],"uses_pep604_syntax":false},{".class":"Instance","args":[{".class":"TupleType","implicit":false,"items":["builtins.str",{".class":"UnionType","items":["builtins.str","builtins.bytes"],"uses_pep604_syntax":false}],"partial_fallback":{".class":"Instance","args":[{".class":"AnyType","missing_import_name":null,"source_any":null,"type_of_any":6}],"extra_attrs":null,"type_ref":"builtins.tuple"}}],"extra_attrs":null,"type_ref":"typing.Sequence"}],"fallback":"builtins.function","from_concatenate":false,"implicit":false,"imprecise_arg_kinds":false,"is_bound":false,"is_ellipsis_args":false,"name":"__init__ of ListFeatureGroupsPager","ret_type":{".class":"NoneType"},"type_guard":null,"type_is":null,"unpack_kwargs":false,"variables":[]}}},"__iter__":{".class":"SymbolTableNode","kind":"Mdef","node":{".class":"FuncDef","abstract_status":0,"arg_kinds":[0],"arg_names":[null],"dataclass_transform_spec":null,"deprecated":null,"flags":["is_trivial_self"],"fullname":"google.cloud.aiplatform_v1beta1.services.feature_registry_service.pagers.ListFeatureGroupsPager.__iter__","name":"__iter__","original_first_arg":"self","type":{".class":"CallableType","arg_kinds":[0],"arg_names":[null],"arg_types":["google.cloud.aiplatform_v1beta1.services.feature_registry_service.pagers.ListFeatureGroupsPager"],"fallback":"builtins.function","from_concatenate":false,"implicit":false,"imprecise_arg_kinds":false,"is_bound":false,"is_ellipsis_args":false,"name":"__iter__ of ListFeatureGroupsPager","ret_type":{".class":"Instance","args":["google.cloud.aiplatform_v1beta1.types.feature_group.FeatureGroup"],"extra_attrs":null,"type_ref":"typing.Iterator"},"type_guard":null,"type_is":null,"unpack_kwargs":false,"variables":[]}}},"__repr__":{".class":"SymbolTableNode","kind":"Mdef","node":{".class":"FuncDef","abstract_status":0,"arg_kinds":[0],"arg_names":[null],"dataclass_transform_spec":null,"deprecated":null,"flags":["is_trivial_self"],"fullname":"google.cloud.aiplatform_v1beta1.services.feature_registry_service.pagers.ListFeatureGroupsPager.__repr__","name":"__repr__","original_first_arg":"self","type":{".class":"CallableType","arg_kinds":[0],"arg_names":[null],"arg_types":["google.cloud.aiplatform_v1beta1.services.feature_registry_service.pagers.ListFeatureGroupsPager"],"fallback":"builtins.function","from_concatenate":false,"implicit":false,"imprecise_arg_kinds":false,"is_bound":false,"is_ellipsis_args":false,"name":"__repr__ of ListFeatureGroupsPager","ret_type":"builtins.str","type_guard":null,"type_is":null,"unpack_kwargs":false,"variables":[]}}},"_metadata":{".class":"SymbolTableNode","implicit":true,"kind":"Mdef","node":{".class":"Var","flags":["is_ready","is_inferred"],"fullname":"google.cloud.aiplatform_v1beta1.services.feature_registry_service.pagers.ListFeatureGroupsPager._metadata","name":"_metadata","setter_type":null,"type":{".class":"Instance","args":[{".class":"TupleType","implicit":false,"items":["builtins.str",{".class":"UnionType","items":["builtins.str","builtins.bytes"],"uses_pep604_syntax":false}],"partial_fallback":{".class":"Instance","args":[{".class":"AnyType","missing_import_name":null,"source_any":null,"type_of_any":6}],"extra_attrs":null,"type_ref":"builtins.tuple"}}],"extra_attrs":null,"type_ref":"typing.Sequence"}}},"_method":{".class":"SymbolTableNode","implicit":true,"kind":"Mdef","node":{".class":"Var","flags":["is_ready","is_inferred"],"fullname":"google.cloud.aiplatform_v1beta1.services.feature_registry_service.pagers.ListFeatureGroupsPager._method","name":"_method","setter_type":null,"type":{".class":"CallableType","arg_kinds":[2,4],"arg_names":[null,null],"arg_types":[{".class":"AnyType","missing_import_name":null,"source_any":null,"type_of_any":2},{".class":"AnyType","missing_import_name":null,"source_any":null,"type_of_any":2}],"fallback":"builtins.function","from_concatenate":false,"implicit":false,"imprecise_arg_kinds":false,"is_bound":false,"is_ellipsis_args":true,"name":null,"ret_type":"google.cloud.aiplatform_v1beta1.types.feature_registry_service.ListFeatureGroupsResponse","type_guard":null,"type_is":null,"unpack_kwargs":false,"variables":[]}}},"_request":{".class":"SymbolTableNode","implicit":true,"kind":"Mdef","node":{".class":"Var","flags":["is_ready","is_inferred"],"fullname":"google.cloud.aiplatform_v1beta1.services.feature_registry_service.pagers.ListFeatureGroupsPager._request","name":"_request","setter_type":null,"type":"google.cloud.aiplatform_v1beta1.types.feature_registry_service.ListFeatureGroupsRequest"}},"_response":{".class":"SymbolTableNode","implicit":true,"kind":"Mdef","node":{".class":"Var","flags":["is_ready","is_inferred"],"fullname":"google.cloud.aiplatform_v1beta1.services.feature_registry_service.pagers.ListFeatureGroupsPager._response","name":"_response","setter_type":null,"type":"google.cloud.aiplatform_v1beta1.types.feature_registry_service.ListFeatureGroupsResponse"}},"_retry":{".class":"SymbolTableNode","implicit":true,"kind":"Mdef","node":{".class":"Var","flags":["is_ready","is_inferred"],"fullname":"google.cloud.aiplatform_v1beta1.services.feature_registry_service.pagers.ListFeatureGroupsPager._retry","name":"_retry","setter_type":null,"type":{".class":"TypeAliasType","args":[],"type_ref":"google.cloud.aiplatform_v1beta1.services.feature_registry_service.pagers.OptionalRetry"}}},"_timeout":{".class":"SymbolTableNode","implicit":true,"kind":"Mdef","node":{".class":"Var","flags":["is_ready","is_inferred"],"fullname":"google.cloud.aiplatform_v1beta1.services.feature_registry_service.pagers.ListFeatureGroupsPager._timeout","name":"_timeout","setter_type":null,"type":{".class":"UnionType","items":["builtins.float","builtins.object"],"uses_pep604_syntax":false}}},"pages":{".class":"SymbolTableNode","kind":"Mdef","node":{".class":"Decorator","func":{".class":"FuncDef","abstract_status":0,"arg_kinds":[0],"arg_names":["self"],"dataclass_transform_spec":null,"deprecated":null,"flags":["is_property","is_generator","is_decorated","is_trivial_self"],"fullname":"google.cloud.aiplatform_v1beta1.services.feature_registry_service.pagers.ListFeatureGroupsPager.pages","name":"pages","original_first_arg":"self","type":{".class":"CallableType","arg_kinds":[0],"arg_names":["self"],"arg_types":["google.cloud.aiplatform_v1beta1.services.feature_registry_service.pagers.ListFeatureGroupsPager"],"fallback":"builtins.function","from_concatenate":false,"implicit":false,"imprecise_arg_kinds":false,"is_bound":false,"is_ellipsis_args":false,"name":"pages of ListFeatureGroupsPager","ret_type":{".class":"Instance","args":["google.cloud.aiplatform_v1beta1.types.feature_registry_service.ListFeatureGroupsResponse"],"extra_attrs":null,"type_ref":"typing.Iterator"},"type_guard":null,"type_is":null,"unpack_kwargs":false,"variables":[]}},"is_overload":false,"var":{".class":"Var","flags":["is_initialized_in_class","is_property","is_ready","is_inferred"],"fullname":"google.cloud.aiplatform_v1beta1.services.feature_registry_service.pagers.ListFeatureGroupsPager.pages","name":"pages","setter_type":null,"type":{".class":"CallableType","arg_kinds":[0],"arg_names":["self"],"arg_types":["google.cloud.aiplatform_v1beta1.services.feature_registry_service.pagers.ListFeatureGroupsPager"],"fallback":"builtins.function","from_concatenate":false,"implicit":false,"imprecise_arg_kinds":false,"is_bound":false,"is_ellipsis_args":false,"name":"pages of ListFeatureGroupsPager","ret_type":{".class":"Instance","args":["google.cloud.aiplatform_v1beta1.types.feature_registry_service.ListFeatureGroupsResponse"],"extra_attrs":null,"type_ref":"typing.Iterator"},"type_guard":null,"type_is":null,"unpack_kwargs":false,"variables":[]}}}}},"self_type":{".class":"TypeVarType","default":{".class":"AnyType","missing_import_name":null,"source_any":null,"type_of_any":4},"fullname":"google.cloud.aiplatform_v1beta1.services.feature_registry_service.pagers.ListFeatureGroupsPager.Self","id":0,"name":"Self","namespace":"","upper_bound":"google.cloud.aiplatform_v1beta1.services.feature_registry_service.pagers.ListFeatureGroupsPager","values":[],"variance":0},"slots":null,"tuple_type":null,"type_vars":[],"typeddict_type":null}},"ListFeatureMonitorJobsAsyncPager":{".class":"SymbolTableNode","kind":"Gdef","node":{".class":"TypeInfo","_promote":[],"abstract_attributes":[],"alt_promote":null,"bases":["builtins.object"],"dataclass_transform_spec":null,"declared_metaclass":null,"defn":{".class":"ClassDef","fullname":"google.cloud.aiplatform_v1beta1.services.feature_registry_service.pagers.ListFeatureMonitorJobsAsyncPager","name":"ListFeatureMonitorJobsAsyncPager","type_vars":[]},"deletable_attributes":[],"deprecated":null,"flags":[],"fullname":"google.cloud.aiplatform_v1beta1.services.feature_registry_service.pagers.ListFeatureMonitorJobsAsyncPager","has_param_spec_type":false,"metaclass_type":null,"metadata":{},"module_name":"google.cloud.aiplatform_v1beta1.services.feature_registry_service.pagers","mro":["google.cloud.aiplatform_v1beta1.services.feature_registry_service.pagers.ListFeatureMonitorJobsAsyncPager","builtins.object"],"names":{".class":"SymbolTable","__aiter__":{".class":"SymbolTableNode","kind":"Mdef","node":{".class":"FuncDef","abstract_status":0,"arg_kinds":[0],"arg_names":["self"],"dataclass_transform_spec":null,"deprecated":null,"flags":["is_trivial_self"],"fullname":"google.cloud.aiplatform_v1beta1.services.feature_registry_service.pagers.ListFeatureMonitorJobsAsyncPager.__aiter__","name":"__aiter__","original_first_arg":"self","type":{".class":"CallableType","arg_kinds":[0],"arg_names":["self"],"arg_types":["google.cloud.aiplatform_v1beta1.services.feature_registry_service.pagers.ListFeatureMonitorJobsAsyncPager"],"fallback":"builtins.function","from_concatenate":false,"implicit":false,"imprecise_arg_kinds":false,"is_bound":false,"is_ellipsis_args":false,"name":"__aiter__ of ListFeatureMonitorJobsAsyncPager","ret_type":{".class":"Instance","args":["google.cloud.aiplatform_v1beta1.types.feature_monitor_job.FeatureMonitorJob"],"extra_attrs":null,"type_ref":"typing.AsyncIterator"},"type_guard":null,"type_is":null,"unpack_kwargs":false,"variables":[]}}},"__getattr__":{".class":"SymbolTableNode","kind":"Mdef","node":{".class":"FuncDef","abstract_status":0,"arg_kinds":[0,0],"arg_names":[null,null],"dataclass_transform_spec":null,"deprecated":null,"flags":["is_trivial_self"],"fullname":"google.cloud.aiplatform_v1beta1.services.feature_registry_service.pagers.ListFeatureMonitorJobsAsyncPager.__getattr__","name":"__getattr__","original_first_arg":"self","type":{".class":"CallableType","arg_kinds":[0,0],"arg_names":[null,null],"arg_types":["google.cloud.aiplatform_v1beta1.services.feature_registry_service.pagers.ListFeatureMonitorJobsAsyncPager","builtins.str"],"fallback":"builtins.function","from_concatenate":false,"implicit":false,"imprecise_arg_kinds":false,"is_bound":false,"is_ellipsis_args":false,"name":"__getattr__ of ListFeatureMonitorJobsAsyncPager","ret_type":{".class":"AnyType","missing_import_name":null,"source_any":null,"type_of_any":2},"type_guard":null,"type_is":null,"unpack_kwargs":false,"variables":[]}}},"__init__":{".class":"SymbolTableNode","kind":"Mdef","node":{".class":"FuncDef","abstract_status":0,"arg_kinds":[0,0,0,0,5,5,5],"arg_names":["self","method","request","response","retry","timeout","metadata"],"dataclass_transform_spec":null,"deprecated":null,"flags":["is_trivial_self"],"fullname":"google.cloud.aiplatform_v1beta1.services.feature_registry_service.pagers.ListFeatureMonitorJobsAsyncPager.__init__","name":"__init__","original_first_arg":"self","type":{".class":"CallableType","arg_kinds":[0,0,0,0,5,5,5],"arg_names":["self","method","request","response","retry","timeout","metadata"],"arg_types":["google.cloud.aiplatform_v1beta1.services.feature_registry_service.pagers.ListFeatureMonitorJobsAsyncPager",{".class":"CallableType","arg_kinds":[2,4],"arg_names":[null,null],"arg_types":[{".class":"AnyType","missing_import_name":null,"source_any":null,"type_of_any":2},{".class":"AnyType","missing_import_name":null,"source_any":null,"type_of_any":2}],"fallback":"builtins.function","from_concatenate":false,"implicit":false,"imprecise_arg_kinds":false,"is_bound":false,"is_ellipsis_args":true,"name":null,"ret_type":{".class":"Instance","args":["google.cloud.aiplatform_v1beta1.types.feature_registry_service.ListFeatureMonitorJobsResponse"],"extra_attrs":null,"type_ref":"typing.Awaitable"},"type_guard":null,"type_is":null,"unpack_kwargs":false,"variables":[]},"google.cloud.aiplatform_v1beta1.types.feature_registry_service.ListFeatureMonitorJobsRequest","google.cloud.aiplatform_v1beta1.types.feature_registry_service.ListFeatureMonitorJobsResponse",{".class":"TypeAliasType","args":[],"type_ref":"google.cloud.aiplatform_v1beta1.services.feature_registry_service.pagers.OptionalAsyncRetry"},{".class":"UnionType","items":["builtins.float","builtins.object"],"uses_pep604_syntax":false},{".class":"Instance","args":[{".class":"TupleType","implicit":false,"items":["builtins.str",{".class":"UnionType","items":["builtins.str","builtins.bytes"],"uses_pep604_syntax":false}],"partial_fallback":{".class":"Instance","args":[{".class":"AnyType","missing_import_name":null,"source_any":null,"type_of_any":6}],"extra_attrs":null,"type_ref":"builtins.tuple"}}],"extra_attrs":null,"type_ref":"typing.Sequence"}],"fallback":"builtins.function","from_concatenate":false,"implicit":false,"imprecise_arg_kinds":false,"is_bound":false,"is_ellipsis_args":false,"name":"__init__ of ListFeatureMonitorJobsAsyncPager","ret_type":{".class":"NoneType"},"type_guard":null,"type_is":null,"unpack_kwargs":false,"variables":[]}}},"__repr__":{".class":"SymbolTableNode","kind":"Mdef","node":{".class":"FuncDef","abstract_status":0,"arg_kinds":[0],"arg_names":[null],"dataclass_transform_spec":null,"deprecated":null,"flags":["is_trivial_self"],"fullname":"google.cloud.aiplatform_v1beta1.services.feature_registry_service.pagers.ListFeatureMonitorJobsAsyncPager.__repr__","name":"__repr__","original_first_arg":"self","type":{".class":"CallableType","arg_kinds":[0],"arg_names":[null],"arg_types":["google.cloud.aiplatform_v1beta1.services.feature_registry_service.pagers.ListFeatureMonitorJobsAsyncPager"],"fallback":"builtins.function","from_concatenate":false,"implicit":false,"imprecise_arg_kinds":false,"is_bound":false,"is_ellipsis_args":false,"name":"__repr__ of ListFeatureMonitorJobsAsyncPager","ret_type":"builtins.str","type_guard":null,"type_is":null,"unpack_kwargs":false,"variables":[]}}},"_metadata":{".class":"SymbolTableNode","implicit":true,"kind":"Mdef","node":{".class":"Var","flags":["is_ready","is_inferred"],"fullname":"google.cloud.aiplatform_v1beta1.services.feature_registry_service.pagers.ListFeatureMonitorJobsAsyncPager._metadata","name":"_metadata","setter_type":null,"type":{".class":"Instance","args":[{".class":"TupleType","implicit":false,"items":["builtins.str",{".class":"UnionType","items":["builtins.str","builtins.bytes"],"uses_pep604_syntax":false}],"partial_fallback":{".class":"Instance","args":[{".class":"AnyType","missing_import_name":null,"source_any":null,"type_of_any":6}],"extra_attrs":null,"type_ref":"builtins.tuple"}}],"extra_attrs":null,"type_ref":"typing.Sequence"}}},"_method":{".class":"SymbolTableNode","implicit":true,"kind":"Mdef","node":{".class":"Var","flags":["is_ready","is_inferred"],"fullname":"google.cloud.aiplatform_v1beta1.services.feature_registry_service.pagers.ListFeatureMonitorJobsAsyncPager._method","name":"_method","setter_type":null,"type":{".class":"CallableType","arg_kinds":[2,4],"arg_names":[null,null],"arg_types":[{".class":"AnyType","missing_import_name":null,"source_any":null,"type_of_any":2},{".class":"AnyType","missing_import_name":null,"source_any":null,"type_of_any":2}],"fallback":"builtins.function","from_concatenate":false,"implicit":false,"imprecise_arg_kinds":false,"is_bound":false,"is_ellipsis_args":true,"name":null,"ret_type":{".class":"Instance","args":["google.cloud.aiplatform_v1beta1.types.feature_registry_service.ListFeatureMonitorJobsResponse"],"extra_attrs":null,"type_ref":"typing.Awaitable"},"type_guard":null,"type_is":null,"unpack_kwargs":false,"variables":[]}}},"_request":{".class":"SymbolTableNode","implicit":true,"kind":"Mdef","node":{".class":"Var","flags":["is_ready","is_inferred"],"fullname":"google.cloud.aiplatform_v1beta1.services.feature_registry_service.pagers.ListFeatureMonitorJobsAsyncPager._request","name":"_request","setter_type":null,"type":"google.cloud.aiplatform_v1beta1.types.feature_registry_service.ListFeatureMonitorJobsRequest"}},"_response":{".class":"SymbolTableNode","implicit":true,"kind":"Mdef","node":{".class":"Var","flags":["is_ready","is_inferred"],"fullname":"google.cloud.aiplatform_v1beta1.services.feature_registry_service.pagers.ListFeatureMonitorJobsAsyncPager._response","name":"_response","setter_type":null,"type":"google.cloud.aiplatform_v1beta1.types.feature_registry_service.ListFeatureMonitorJobsResponse"}},"_retry":{".class":"SymbolTableNode","implicit":true,"kind":"Mdef","node":{".class":"Var","flags":["is_ready","is_inferred"],"fullname":"google.cloud.aiplatform_v1beta1.services.feature_registry_service.pagers.ListFeatureMonitorJobsAsyncPager._retry","name":"_retry","setter_type":null,"type":{".class":"TypeAliasType","args":[],"type_ref":"google.cloud.aiplatform_v1beta1.services.feature_registry_service.pagers.OptionalAsyncRetry"}}},"_timeout":{".class":"SymbolTableNode","implicit":true,"kind":"Mdef","node":{".class":"Var","flags":["is_ready","is_inferred"],"fullname":"google.cloud.aiplatform_v1beta1.services.feature_registry_service.pagers.ListFeatureMonitorJobsAsyncPager._timeout","name":"_timeout","setter_type":null,"type":{".class":"UnionType","items":["builtins.float","builtins.object"],"uses_pep604_syntax":false}}},"pages":{".class":"SymbolTableNode","kind":"Mdef","node":{".class":"Decorator","func":{".class":"FuncDef","abstract_status":0,"arg_kinds":[0],"arg_names":["self"],"dataclass_transform_spec":null,"deprecated":null,"flags":["is_property","is_generator","is_coroutine","is_async_generator","is_decorated","is_trivial_self"],"fullname":"google.cloud.aiplatform_v1beta1.services.feature_registry_service.pagers.ListFeatureMonitorJobsAsyncPager.pages","name":"pages","original_first_arg":"self","type":{".class":"CallableType","arg_kinds":[0],"arg_names":["self"],"arg_types":["google.cloud.aiplatform_v1beta1.services.feature_registry_service.pagers.ListFeatureMonitorJobsAsyncPager"],"fallback":"builtins.function","from_concatenate":false,"implicit":false,"imprecise_arg_kinds":false,"is_bound":false,"is_ellipsis_args":false,"name":"pages of ListFeatureMonitorJobsAsyncPager","ret_type":{".class":"Instance","args":["google.cloud.aiplatform_v1beta1.types.feature_registry_service.ListFeatureMonitorJobsResponse"],"extra_attrs":null,"type_ref":"typing.AsyncIterator"},"type_guard":null,"type_is":null,"unpack_kwargs":false,"variables":[]}},"is_overload":false,"var":{".class":"Var","flags":["is_initialized_in_class","is_property","is_ready","is_inferred"],"fullname":"google.cloud.aiplatform_v1beta1.services.feature_registry_service.pagers.ListFeatureMonitorJobsAsyncPager.pages","name":"pages","setter_type":null,"type":{".class":"CallableType","arg_kinds":[0],"arg_names":["self"],"arg_types":["google.cloud.aiplatform_v1beta1.services.feature_registry_service.pagers.ListFeatureMonitorJobsAsyncPager"],"fallback":"builtins.function","from_concatenate":false,"implicit":false,"imprecise_arg_kinds":false,"is_bound":false,"is_ellipsis_args":false,"name":"pages of ListFeatureMonitorJobsAsyncPager","ret_type":{".class":"Instance","args":["google.cloud.aiplatform_v1beta1.types.feature_registry_service.ListFeatureMonitorJobsResponse"],"extra_attrs":null,"type_ref":"typing.AsyncIterator"},"type_guard":null,"type_is":null,"unpack_kwargs":false,"variables":[]}}}}},"self_type":{".class":"TypeVarType","default":{".class":"AnyType","missing_import_name":null,"source_any":null,"type_of_any":4},"fullname":"google.cloud.aiplatform_v1beta1.services.feature_registry_service.pagers.ListFeatureMonitorJobsAsyncPager.Self","id":0,"name":"Self","namespace":"","upper_bound":"google.cloud.aiplatform_v1beta1.services.feature_registry_service.pagers.ListFeatureMonitorJobsAsyncPager","values":[],"variance":0},"slots":null,"tuple_type":null,"type_vars":[],"typeddict_type":null}},"ListFeatureMonitorJobsPager":{".class":"SymbolTableNode","kind":"Gdef","node":{".class":"TypeInfo","_promote":[],"abstract_attributes":[],"alt_promote":null,"bases":["builtins.object"],"dataclass_transform_spec":null,"declared_metaclass":null,"defn":{".class":"ClassDef","fullname":"google.cloud.aiplatform_v1beta1.services.feature_registry_service.pagers.ListFeatureMonitorJobsPager","name":"ListFeatureMonitorJobsPager","type_vars":[]},"deletable_attributes":[],"deprecated":null,"flags":[],"fullname":"google.cloud.aiplatform_v1beta1.services.feature_registry_service.pagers.ListFeatureMonitorJobsPager","has_param_spec_type":false,"metaclass_type":null,"metadata":{},"module_name":"google.cloud.aiplatform_v1beta1.services.feature_registry_service.pagers","mro":["google.cloud.aiplatform_v1beta1.services.feature_registry_service.pagers.ListFeatureMonitorJobsPager","builtins.object"],"names":{".class":"SymbolTable","__getattr__":{".class":"SymbolTableNode","kind":"Mdef","node":{".class":"FuncDef","abstract_status":0,"arg_kinds":[0,0],"arg_names":[null,null],"dataclass_transform_spec":null,"deprecated":null,"flags":["is_trivial_self"],"fullname":"google.cloud.aiplatform_v1beta1.services.feature_registry_service.pagers.ListFeatureMonitorJobsPager.__getattr__","name":"__getattr__","original_first_arg":"self","type":{".class":"CallableType","arg_kinds":[0,0],"arg_names":[null,null],"arg_types":["google.cloud.aiplatform_v1beta1.services.feature_registry_service.pagers.ListFeatureMonitorJobsPager","builtins.str"],"fallback":"builtins.function","from_concatenate":false,"implicit":false,"imprecise_arg_kinds":false,"is_bound":false,"is_ellipsis_args":false,"name":"__getattr__ of ListFeatureMonitorJobsPager","ret_type":{".class":"AnyType","missing_import_name":null,"source_any":null,"type_of_any":2},"type_guard":null,"type_is":null,"unpack_kwargs":false,"variables":[]}}},"__init__":{".class":"SymbolTableNode","kind":"Mdef","node":{".class":"FuncDef","abstract_status":0,"arg_kinds":[0,0,0,0,5,5,5],"arg_names":["self","method","request","response","retry","timeout","metadata"],"dataclass_transform_spec":null,"deprecated":null,"flags":["is_trivial_self"],"fullname":"google.cloud.aiplatform_v1beta1.services.feature_registry_service.pagers.ListFeatureMonitorJobsPager.__init__","name":"__init__","original_first_arg":"self","type":{".class":"CallableType","arg_kinds":[0,0,0,0,5,5,5],"arg_names":["self","method","request","response","retry","timeout","metadata"],"arg_types":["google.cloud.aiplatform_v1beta1.services.feature_registry_service.pagers.ListFeatureMonitorJobsPager",{".class":"CallableType","arg_kinds":[2,4],"arg_names":[null,null],"arg_types":[{".class":"AnyType","missing_import_name":null,"source_any":null,"type_of_any":2},{".class":"AnyType","missing_import_name":null,"source_any":null,"type_of_any":2}],"fallback":"builtins.function","from_concatenate":false,"implicit":false,"imprecise_arg_kinds":false,"is_bound":false,"is_ellipsis_args":true,"name":null,"ret_type":"google.cloud.aiplatform_v1beta1.types.feature_registry_service.ListFeatureMonitorJobsResponse","type_guard":null,"type_is":null,"unpack_kwargs":false,"variables":[]},"google.cloud.aiplatform_v1beta1.types.feature_registry_service.ListFeatureMonitorJobsRequest","google.cloud.aiplatform_v1beta1.types.feature_registry_service.ListFeatureMonitorJobsResponse",{".class":"TypeAliasType","args":[],"type_ref":"google.cloud.aiplatform_v1beta1.services.feature_registry_service.pagers.OptionalRetry"},{".class":"UnionType","items":["builtins.float","builtins.object"],"uses_pep604_syntax":false},{".class":"Instance","args":[{".class":"TupleType","implicit":false,"items":["builtins.str",{".class":"UnionType","items":["builtins.str","builtins.bytes"],"uses_pep604_syntax":false}],"partial_fallback":{".class":"Instance","args":[{".class":"AnyType","missing_import_name":null,"source_any":null,"type_of_any":6}],"extra_attrs":null,"type_ref":"builtins.tuple"}}],"extra_attrs":null,"type_ref":"typing.Sequence"}],"fallback":"builtins.function","from_concatenate":false,"implicit":false,"imprecise_arg_kinds":false,"is_bound":false,"is_ellipsis_args":false,"name":"__init__ of ListFeatureMonitorJobsPager","ret_type":{".class":"NoneType"},"type_guard":null,"type_is":null,"unpack_kwargs":false,"variables":[]}}},"__iter__":{".class":"SymbolTableNode","kind":"Mdef","node":{".class":"FuncDef","abstract_status":0,"arg_kinds":[0],"arg_names":[null],"dataclass_transform_spec":null,"deprecated":null,"flags":["is_trivial_self"],"fullname":"google.cloud.aiplatform_v1beta1.services.feature_registry_service.pagers.ListFeatureMonitorJobsPager.__iter__","name":"__iter__","original_first_arg":"self","type":{".class":"CallableType","arg_kinds":[0],"arg_names":[null],"arg_types":["google.cloud.aiplatform_v1beta1.services.feature_registry_service.pagers.ListFeatureMonitorJobsPager"],"fallback":"builtins.function","from_concatenate":false,"implicit":false,"imprecise_arg_kinds":false,"is_bound":false,"is_ellipsis_args":false,"name":"__iter__ of ListFeatureMonitorJobsPager","ret_type":{".class":"Instance","args":["google.cloud.aiplatform_v1beta1.types.feature_monitor_job.FeatureMonitorJob"],"extra_attrs":null,"type_ref":"typing.Iterator"},"type_guard":null,"type_is":null,"unpack_kwargs":false,"variables":[]}}},"__repr__":{".class":"SymbolTableNode","kind":"Mdef","node":{".class":"FuncDef","abstract_status":0,"arg_kinds":[0],"arg_names":[null],"dataclass_transform_spec":null,"deprecated":null,"flags":["is_trivial_self"],"fullname":"google.cloud.aiplatform_v1beta1.services.feature_registry_service.pagers.ListFeatureMonitorJobsPager.__repr__","name":"__repr__","original_first_arg":"self","type":{".class":"CallableType","arg_kinds":[0],"arg_names":[null],"arg_types":["google.cloud.aiplatform_v1beta1.services.feature_registry_service.pagers.ListFeatureMonitorJobsPager"],"fallback":"builtins.function","from_concatenate":false,"implicit":false,"imprecise_arg_kinds":false,"is_bound":false,"is_ellipsis_args":false,"name":"__repr__ of ListFeatureMonitorJobsPager","ret_type":"builtins.str","type_guard":null,"type_is":null,"unpack_kwargs":false,"variables":[]}}},"_metadata":{".class":"SymbolTableNode","implicit":true,"kind":"Mdef","node":{".class":"Var","flags":["is_ready","is_inferred"],"fullname":"google.cloud.aiplatform_v1beta1.services.feature_registry_service.pagers.ListFeatureMonitorJobsPager._metadata","name":"_metadata","setter_type":null,"type":{".class":"Instance","args":[{".class":"TupleType","implicit":false,"items":["builtins.str",{".class":"UnionType","items":["builtins.str","builtins.bytes"],"uses_pep604_syntax":false}],"partial_fallback":{".class":"Instance","args":[{".class":"AnyType","missing_import_name":null,"source_any":null,"type_of_any":6}],"extra_attrs":null,"type_ref":"builtins.tuple"}}],"extra_attrs":null,"type_ref":"typing.Sequence"}}},"_method":{".class":"SymbolTableNode","implicit":true,"kind":"Mdef","node":{".class":"Var","flags":["is_ready","is_inferred"],"fullname":"google.cloud.aiplatform_v1beta1.services.feature_registry_service.pagers.ListFeatureMonitorJobsPager._method","name":"_method","setter_type":null,"type":{".class":"CallableType","arg_kinds":[2,4],"arg_names":[null,null],"arg_types":[{".class":"AnyType","missing_import_name":null,"source_any":null,"type_of_any":2},{".class":"AnyType","missing_import_name":null,"source_any":null,"type_of_any":2}],"fallback":"builtins.function","from_concatenate":false,"implicit":false,"imprecise_arg_kinds":false,"is_bound":false,"is_ellipsis_args":true,"name":null,"ret_type":"google.cloud.aiplatform_v1beta1.types.feature_registry_service.ListFeatureMonitorJobsResponse","type_guard":null,"type_is":null,"unpack_kwargs":false,"variables":[]}}},"_request":{".class":"SymbolTableNode","implicit":true,"kind":"Mdef","node":{".class":"Var","flags":["is_ready","is_inferred"],"fullname":"google.cloud.aiplatform_v1beta1.services.feature_registry_service.pagers.ListFeatureMonitorJobsPager._request","name":"_request","setter_type":null,"type":"google.cloud.aiplatform_v1beta1.types.feature_registry_service.ListFeatureMonitorJobsRequest"}},"_response":{".class":"SymbolTableNode","implicit":true,"kind":"Mdef","node":{".class":"Var","flags":["is_ready","is_inferred"],"fullname":"google.cloud.aiplatform_v1beta1.services.feature_registry_service.pagers.ListFeatureMonitorJobsPager._response","name":"_response","setter_type":null,"type":"google.cloud.aiplatform_v1beta1.types.feature_registry_service.ListFeatureMonitorJobsResponse"}},"_retry":{".class":"SymbolTableNode","implicit":true,"kind":"Mdef","node":{".class":"Var","flags":["is_ready","is_inferred"],"fullname":"google.cloud.aiplatform_v1beta1.services.feature_registry_service.pagers.ListFeatureMonitorJobsPager._retry","name":"_retry","setter_type":null,"type":{".class":"TypeAliasType","args":[],"type_ref":"google.cloud.aiplatform_v1beta1.services.feature_registry_service.pagers.OptionalRetry"}}},"_timeout":{".class":"SymbolTableNode","implicit":true,"kind":"Mdef","node":{".class":"Var","flags":["is_ready","is_inferred"],"fullname":"google.cloud.aiplatform_v1beta1.services.feature_registry_service.pagers.ListFeatureMonitorJobsPager._timeout","name":"_timeout","setter_type":null,"type":{".class":"UnionType","items":["builtins.float","builtins.object"],"uses_pep604_syntax":false}}},"pages":{".class":"SymbolTableNode","kind":"Mdef","node":{".class":"Decorator","func":{".class":"FuncDef","abstract_status":0,"arg_kinds":[0],"arg_names":["self"],"dataclass_transform_spec":null,"deprecated":null,"flags":["is_property","is_generator","is_decorated","is_trivial_self"],"fullname":"google.cloud.aiplatform_v1beta1.services.feature_registry_service.pagers.ListFeatureMonitorJobsPager.pages","name":"pages","original_first_arg":"self","type":{".class":"CallableType","arg_kinds":[0],"arg_names":["self"],"arg_types":["google.cloud.aiplatform_v1beta1.services.feature_registry_service.pagers.ListFeatureMonitorJobsPager"],"fallback":"builtins.function","from_concatenate":false,"implicit":false,"imprecise_arg_kinds":false,"is_bound":false,"is_ellipsis_args":false,"name":"pages of ListFeatureMonitorJobsPager","ret_type":{".class":"Instance","args":["google.cloud.aiplatform_v1beta1.types.feature_registry_service.ListFeatureMonitorJobsResponse"],"extra_attrs":null,"type_ref":"typing.Iterator"},"type_guard":null,"type_is":null,"unpack_kwargs":false,"variables":[]}},"is_overload":false,"var":{".class":"Var","flags":["is_initialized_in_class","is_property","is_ready","is_inferred"],"fullname":"google.cloud.aiplatform_v1beta1.services.feature_registry_service.pagers.ListFeatureMonitorJobsPager.pages","name":"pages","setter_type":null,"type":{".class":"CallableType","arg_kinds":[0],"arg_names":["self"],"arg_types":["google.cloud.aiplatform_v1beta1.services.feature_registry_service.pagers.ListFeatureMonitorJobsPager"],"fallback":"builtins.function","from_concatenate":false,"implicit":false,"imprecise_arg_kinds":false,"is_bound":false,"is_ellipsis_args":false,"name":"pages of ListFeatureMonitorJobsPager","ret_type":{".class":"Instance","args":["google.cloud.aiplatform_v1beta1.types.feature_registry_service.ListFeatureMonitorJobsResponse"],"extra_attrs":null,"type_ref":"typing.Iterator"},"type_guard":null,"type_is":null,"unpack_kwargs":false,"variables":[]}}}}},"self_type":{".class":"TypeVarType","default":{".class":"AnyType","missing_import_name":null,"source_any":null,"type_of_any":4},"fullname":"google.cloud.aiplatform_v1beta1.services.feature_registry_service.pagers.ListFeatureMonitorJobsPager.Self","id":0,"name":"Self","namespace":"","upper_bound":"google.cloud.aiplatform_v1beta1.services.feature_registry_service.pagers.ListFeatureMonitorJobsPager","values":[],"variance":0},"slots":null,"tuple_type":null,"type_vars":[],"typeddict_type":null}},"ListFeatureMonitorsAsyncPager":{".class":"SymbolTableNode","kind":"Gdef","node":{".class":"TypeInfo","_promote":[],"abstract_attributes":[],"alt_promote":null,"bases":["builtins.object"],"dataclass_transform_spec":null,"declared_metaclass":null,"defn":{".class":"ClassDef","fullname":"google.cloud.aiplatform_v1beta1.services.feature_registry_service.pagers.ListFeatureMonitorsAsyncPager","name":"ListFeatureMonitorsAsyncPager","type_vars":[]},"deletable_attributes":[],"deprecated":null,"flags":[],"fullname":"google.cloud.aiplatform_v1beta1.services.feature_registry_service.pagers.ListFeatureMonitorsAsyncPager","has_param_spec_type":false,"metaclass_type":null,"metadata":{},"module_name":"google.cloud.aiplatform_v1beta1.services.feature_registry_service.pagers","mro":["google.cloud.aiplatform_v1beta1.services.feature_registry_service.pagers.ListFeatureMonitorsAsyncPager","builtins.object"],"names":{".class":"SymbolTable","__aiter__":{".class":"SymbolTableNode","kind":"Mdef","node":{".class":"FuncDef","abstract_status":0,"arg_kinds":[0],"arg_names":["self"],"dataclass_transform_spec":null,"deprecated":null,"flags":["is_trivial_self"],"fullname":"google.cloud.aiplatform_v1beta1.services.feature_registry_service.pagers.ListFeatureMonitorsAsyncPager.__aiter__","name":"__aiter__","original_first_arg":"self","type":{".class":"CallableType","arg_kinds":[0],"arg_names":["self"],"arg_types":["google.cloud.aiplatform_v1beta1.services.feature_registry_service.pagers.ListFeatureMonitorsAsyncPager"],"fallback":"builtins.function","from_concatenate":false,"implicit":false,"imprecise_arg_kinds":false,"is_bound":false,"is_ellipsis_args":false,"name":"__aiter__ of ListFeatureMonitorsAsyncPager","ret_type":{".class":"Instance","args":["google.cloud.aiplatform_v1beta1.types.feature_monitor.FeatureMonitor"],"extra_attrs":null,"type_ref":"typing.AsyncIterator"},"type_guard":null,"type_is":null,"unpack_kwargs":false,"variables":[]}}},"__getattr__":{".class":"SymbolTableNode","kind":"Mdef","node":{".class":"FuncDef","abstract_status":0,"arg_kinds":[0,0],"arg_names":[null,null],"dataclass_transform_spec":null,"deprecated":null,"flags":["is_trivial_self"],"fullname":"google.cloud.aiplatform_v1beta1.services.feature_registry_service.pagers.ListFeatureMonitorsAsyncPager.__getattr__","name":"__getattr__","original_first_arg":"self","type":{".class":"CallableType","arg_kinds":[0,0],"arg_names":[null,null],"arg_types":["google.cloud.aiplatform_v1beta1.services.feature_registry_service.pagers.ListFeatureMonitorsAsyncPager","builtins.str"],"fallback":"builtins.function","from_concatenate":false,"implicit":false,"imprecise_arg_kinds":false,"is_bound":false,"is_ellipsis_args":false,"name":"__getattr__ of ListFeatureMonitorsAsyncPager","ret_type":{".class":"AnyType","missing_import_name":null,"source_any":null,"type_of_any":2},"type_guard":null,"type_is":null,"unpack_kwargs":false,"variables":[]}}},"__init__":{".class":"SymbolTableNode","kind":"Mdef","node":{".class":"FuncDef","abstract_status":0,"arg_kinds":[0,0,0,0,5,5,5],"arg_names":["self","method","request","response","retry","timeout","metadata"],"dataclass_transform_spec":null,"deprecated":null,"flags":["is_trivial_self"],"fullname":"google.cloud.aiplatform_v1beta1.services.feature_registry_service.pagers.ListFeatureMonitorsAsyncPager.__init__","name":"__init__","original_first_arg":"self","type":{".class":"CallableType","arg_kinds":[0,0,0,0,5,5,5],"arg_names":["self","method","request","response","retry","timeout","metadata"],"arg_types":["google.cloud.aiplatform_v1beta1.services.feature_registry_service.pagers.ListFeatureMonitorsAsyncPager",{".class":"CallableType","arg_kinds":[2,4],"arg_names":[null,null],"arg_types":[{".class":"AnyType","missing_import_name":null,"source_any":null,"type_of_any":2},{".class":"AnyType","missing_import_name":null,"source_any":null,"type_of_any":2}],"fallback":"builtins.function","from_concatenate":false,"implicit":false,"imprecise_arg_kinds":false,"is_bound":false,"is_ellipsis_args":true,"name":null,"ret_type":{".class":"Instance","args":["google.cloud.aiplatform_v1beta1.types.feature_registry_service.ListFeatureMonitorsResponse"],"extra_attrs":null,"type_ref":"typing.Awaitable"},"type_guard":null,"type_is":null,"unpack_kwargs":false,"variables":[]},"google.cloud.aiplatform_v1beta1.types.feature_registry_service.ListFeatureMonitorsRequest","google.cloud.aiplatform_v1beta1.types.feature_registry_service.ListFeatureMonitorsResponse",{".class":"TypeAliasType","args":[],"type_ref":"google.cloud.aiplatform_v1beta1.services.feature_registry_service.pagers.OptionalAsyncRetry"},{".class":"UnionType","items":["builtins.float","builtins.object"],"uses_pep604_syntax":false},{".class":"Instance","args":[{".class":"TupleType","implicit":false,"items":["builtins.str",{".class":"UnionType","items":["builtins.str","builtins.bytes"],"uses_pep604_syntax":false}],"partial_fallback":{".class":"Instance","args":[{".class":"AnyType","missing_import_name":null,"source_any":null,"type_of_any":6}],"extra_attrs":null,"type_ref":"builtins.tuple"}}],"extra_attrs":null,"type_ref":"typing.Sequence"}],"fallback":"builtins.function","from_concatenate":false,"implicit":false,"imprecise_arg_kinds":false,"is_bound":false,"is_ellipsis_args":false,"name":"__init__ of ListFeatureMonitorsAsyncPager","ret_type":{".class":"NoneType"},"type_guard":null,"type_is":null,"unpack_kwargs":false,"variables":[]}}},"__repr__":{".class":"SymbolTableNode","kind":"Mdef","node":{".class":"FuncDef","abstract_status":0,"arg_kinds":[0],"arg_names":[null],"dataclass_transform_spec":null,"deprecated":null,"flags":["is_trivial_self"],"fullname":"google.cloud.aiplatform_v1beta1.services.feature_registry_service.pagers.ListFeatureMonitorsAsyncPager.__repr__","name":"__repr__","original_first_arg":"self","type":{".class":"CallableType","arg_kinds":[0],"arg_names":[null],"arg_types":["google.cloud.aiplatform_v1beta1.services.feature_registry_service.pagers.ListFeatureMonitorsAsyncPager"],"fallback":"builtins.function","from_concatenate":false,"implicit":false,"imprecise_arg_kinds":false,"is_bound":false,"is_ellipsis_args":false,"name":"__repr__ of ListFeatureMonitorsAsyncPager","ret_type":"builtins.str","type_guard":null,"type_is":null,"unpack_kwargs":false,"variables":[]}}},"_metadata":{".class":"SymbolTableNode","implicit":true,"kind":"Mdef","node":{".class":"Var","flags":["is_ready","is_inferred"],"fullname":"google.cloud.aiplatform_v1beta1.services.feature_registry_service.pagers.ListFeatureMonitorsAsyncPager._metadata","name":"_metadata","setter_type":null,"type":{".class":"Instance","args":[{".class":"TupleType","implicit":false,"items":["builtins.str",{".class":"UnionType","items":["builtins.str","builtins.bytes"],"uses_pep604_syntax":false}],"partial_fallback":{".class":"Instance","args":[{".class":"AnyType","missing_import_name":null,"source_any":null,"type_of_any":6}],"extra_attrs":null,"type_ref":"builtins.tuple"}}],"extra_attrs":null,"type_ref":"typing.Sequence"}}},"_method":{".class":"SymbolTableNode","implicit":true,"kind":"Mdef","node":{".class":"Var","flags":["is_ready","is_inferred"],"fullname":"google.cloud.aiplatform_v1beta1.services.feature_registry_service.pagers.ListFeatureMonitorsAsyncPager._method","name":"_method","setter_type":null,"type":{".class":"CallableType","arg_kinds":[2,4],"arg_names":[null,null],"arg_types":[{".class":"AnyType","missing_import_name":null,"source_any":null,"type_of_any":2},{".class":"AnyType","missing_import_name":null,"source_any":null,"type_of_any":2}],"fallback":"builtins.function","from_concatenate":false,"implicit":false,"imprecise_arg_kinds":false,"is_bound":false,"is_ellipsis_args":true,"name":null,"ret_type":{".class":"Instance","args":["google.cloud.aiplatform_v1beta1.types.feature_registry_service.ListFeatureMonitorsResponse"],"extra_attrs":null,"type_ref":"typing.Awaitable"},"type_guard":null,"type_is":null,"unpack_kwargs":false,"variables":[]}}},"_request":{".class":"SymbolTableNode","implicit":true,"kind":"Mdef","node":{".class":"Var","flags":["is_ready","is_inferred"],"fullname":"google.cloud.aiplatform_v1beta1.services.feature_registry_service.pagers.ListFeatureMonitorsAsyncPager._request","name":"_request","setter_type":null,"type":"google.cloud.aiplatform_v1beta1.types.feature_registry_service.ListFeatureMonitorsRequest"}},"_response":{".class":"SymbolTableNode","implicit":true,"kind":"Mdef","node":{".class":"Var","flags":["is_ready","is_inferred"],"fullname":"google.cloud.aiplatform_v1beta1.services.feature_registry_service.pagers.ListFeatureMonitorsAsyncPager._response","name":"_response","setter_type":null,"type":"google.cloud.aiplatform_v1beta1.types.feature_registry_service.ListFeatureMonitorsResponse"}},"_retry":{".class":"SymbolTableNode","implicit":true,"kind":"Mdef","node":{".class":"Var","flags":["is_ready","is_inferred"],"fullname":"google.cloud.aiplatform_v1beta1.services.feature_registry_service.pagers.ListFeatureMonitorsAsyncPager._retry","name":"_retry","setter_type":null,"type":{".class":"TypeAliasType","args":[],"type_ref":"google.cloud.aiplatform_v1beta1.services.feature_registry_service.pagers.OptionalAsyncRetry"}}},"_timeout":{".class":"SymbolTableNode","implicit":true,"kind":"Mdef","node":{".class":"Var","flags":["is_ready","is_inferred"],"fullname":"google.cloud.aiplatform_v1beta1.services.feature_registry_service.pagers.ListFeatureMonitorsAsyncPager._timeout","name":"_timeout","setter_type":null,"type":{".class":"UnionType","items":["builtins.float","builtins.object"],"uses_pep604_syntax":false}}},"pages":{".class":"SymbolTableNode","kind":"Mdef","node":{".class":"Decorator","func":{".class":"FuncDef","abstract_status":0,"arg_kinds":[0],"arg_names":["self"],"dataclass_transform_spec":null,"deprecated":null,"flags":["is_property","is_generator","is_coroutine","is_async_generator","is_decorated","is_trivial_self"],"fullname":"google.cloud.aiplatform_v1beta1.services.feature_registry_service.pagers.ListFeatureMonitorsAsyncPager.pages","name":"pages","original_first_arg":"self","type":{".class":"CallableType","arg_kinds":[0],"arg_names":["self"],"arg_types":["google.cloud.aiplatform_v1beta1.services.feature_registry_service.pagers.ListFeatureMonitorsAsyncPager"],"fallback":"builtins.function","from_concatenate":false,"implicit":false,"imprecise_arg_kinds":false,"is_bound":false,"is_ellipsis_args":false,"name":"pages of ListFeatureMonitorsAsyncPager","ret_type":{".class":"Instance","args":["google.cloud.aiplatform_v1beta1.types.feature_registry_service.ListFeatureMonitorsResponse"],"extra_attrs":null,"type_ref":"typing.AsyncIterator"},"type_guard":null,"type_is":null,"unpack_kwargs":false,"variables":[]}},"is_overload":false,"var":{".class":"Var","flags":["is_initialized_in_class","is_property","is_ready","is_inferred"],"fullname":"google.cloud.aiplatform_v1beta1.services.feature_registry_service.pagers.ListFeatureMonitorsAsyncPager.pages","name":"pages","setter_type":null,"type":{".class":"CallableType","arg_kinds":[0],"arg_names":["self"],"arg_types":["google.cloud.aiplatform_v1beta1.services.feature_registry_service.pagers.ListFeatureMonitorsAsyncPager"],"fallback":"builtins.function","from_concatenate":false,"implicit":false,"imprecise_arg_kinds":false,"is_bound":false,"is_ellipsis_args":false,"name":"pages of ListFeatureMonitorsAsyncPager","ret_type":{".class":"Instance","args":["google.cloud.aiplatform_v1beta1.types.feature_registry_service.ListFeatureMonitorsResponse"],"extra_attrs":null,"type_ref":"typing.AsyncIterator"},"type_guard":null,"type_is":null,"unpack_kwargs":false,"variables":[]}}}}},"self_type":{".class":"TypeVarType","default":{".class":"AnyType","missing_import_name":null,"source_any":null,"type_of_any":4},"fullname":"google.cloud.aiplatform_v1beta1.services.feature_registry_service.pagers.ListFeatureMonitorsAsyncPager.Self","id":0,"name":"Self","namespace":"","upper_bound":"google.cloud.aiplatform_v1beta1.services.feature_registry_service.pagers.ListFeatureMonitorsAsyncPager","values":[],"variance":0},"slots":null,"tuple_type":null,"type_vars":[],"typeddict_type":null}},"ListFeatureMonitorsPager":{".class":"SymbolTableNode","kind":"Gdef","node":{".class":"TypeInfo","_promote":[],"abstract_attributes":[],"alt_promote":null,"bases":["builtins.object"],"dataclass_transform_spec":null,"declared_metaclass":null,"defn":{".class":"ClassDef","fullname":"google.cloud.aiplatform_v1beta1.services.feature_registry_service.pagers.ListFeatureMonitorsPager","name":"ListFeatureMonitorsPager","type_vars":[]},"deletable_attributes":[],"deprecated":null,"flags":[],"fullname":"google.cloud.aiplatform_v1beta1.services.feature_registry_service.pagers.ListFeatureMonitorsPager","has_param_spec_type":false,"metaclass_type":null,"metadata":{},"module_name":"google.cloud.aiplatform_v1beta1.services.feature_registry_service.pagers","mro":["google.cloud.aiplatform_v1beta1.services.feature_registry_service.pagers.ListFeatureMonitorsPager","builtins.object"],"names":{".class":"SymbolTable","__getattr__":{".class":"SymbolTableNode","kind":"Mdef","node":{".class":"FuncDef","abstract_status":0,"arg_kinds":[0,0],"arg_names":[null,null],"dataclass_transform_spec":null,"deprecated":null,"flags":["is_trivial_self"],"fullname":"google.cloud.aiplatform_v1beta1.services.feature_registry_service.pagers.ListFeatureMonitorsPager.__getattr__","name":"__getattr__","original_first_arg":"self","type":{".class":"CallableType","arg_kinds":[0,0],"arg_names":[null,null],"arg_types":["google.cloud.aiplatform_v1beta1.services.feature_registry_service.pagers.ListFeatureMonitorsPager","builtins.str"],"fallback":"builtins.function","from_concatenate":false,"implicit":false,"imprecise_arg_kinds":false,"is_bound":false,"is_ellipsis_args":false,"name":"__getattr__ of ListFeatureMonitorsPager","ret_type":{".class":"AnyType","missing_import_name":null,"source_any":null,"type_of_any":2},"type_guard":null,"type_is":null,"unpack_kwargs":false,"variables":[]}}},"__init__":{".class":"SymbolTableNode","kind":"Mdef","node":{".class":"FuncDef","abstract_status":0,"arg_kinds":[0,0,0,0,5,5,5],"arg_names":["self","method","request","response","retry","timeout","metadata"],"dataclass_transform_spec":null,"deprecated":null,"flags":["is_trivial_self"],"fullname":"google.cloud.aiplatform_v1beta1.services.feature_registry_service.pagers.ListFeatureMonitorsPager.__init__","name":"__init__","original_first_arg":"self","type":{".class":"CallableType","arg_kinds":[0,0,0,0,5,5,5],"arg_names":["self","method","request","response","retry","timeout","metadata"],"arg_types":["google.cloud.aiplatform_v1beta1.services.feature_registry_service.pagers.ListFeatureMonitorsPager",{".class":"CallableType","arg_kinds":[2,4],"arg_names":[null,null],"arg_types":[{".class":"AnyType","missing_import_name":null,"source_any":null,"type_of_any":2},{".class":"AnyType","missing_import_name":null,"source_any":null,"type_of_any":2}],"fallback":"builtins.function","from_concatenate":false,"implicit":false,"imprecise_arg_kinds":false,"is_bound":false,"is_ellipsis_args":true,"name":null,"ret_type":"google.cloud.aiplatform_v1beta1.types.feature_registry_service.ListFeatureMonitorsResponse","type_guard":null,"type_is":null,"unpack_kwargs":false,"variables":[]},"google.cloud.aiplatform_v1beta1.types.feature_registry_service.ListFeatureMonitorsRequest","google.cloud.aiplatform_v1beta1.types.feature_registry_service.ListFeatureMonitorsResponse",{".class":"TypeAliasType","args":[],"type_ref":"google.cloud.aiplatform_v1beta1.services.feature_registry_service.pagers.OptionalRetry"},{".class":"UnionType","items":["builtins.float","builtins.object"],"uses_pep604_syntax":false},{".class":"Instance","args":[{".class":"TupleType","implicit":false,"items":["builtins.str",{".class":"UnionType","items":["builtins.str","builtins.bytes"],"uses_pep604_syntax":false}],"partial_fallback":{".class":"Instance","args":[{".class":"AnyType","missing_import_name":null,"source_any":null,"type_of_any":6}],"extra_attrs":null,"type_ref":"builtins.tuple"}}],"extra_attrs":null,"type_ref":"typing.Sequence"}],"fallback":"builtins.function","from_concatenate":false,"implicit":false,"imprecise_arg_kinds":false,"is_bound":false,"is_ellipsis_args":false,"name":"__init__ of ListFeatureMonitorsPager","ret_type":{".class":"NoneType"},"type_guard":null,"type_is":null,"unpack_kwargs":false,"variables":[]}}},"__iter__":{".class":"SymbolTableNode","kind":"Mdef","node":{".class":"FuncDef","abstract_status":0,"arg_kinds":[0],"arg_names":[null],"dataclass_transform_spec":null,"deprecated":null,"flags":["is_trivial_self"],"fullname":"google.cloud.aiplatform_v1beta1.services.feature_registry_service.pagers.ListFeatureMonitorsPager.__iter__","name":"__iter__","original_first_arg":"self","type":{".class":"CallableType","arg_kinds":[0],"arg_names":[null],"arg_types":["google.cloud.aiplatform_v1beta1.services.feature_registry_service.pagers.ListFeatureMonitorsPager"],"fallback":"builtins.function","from_concatenate":false,"implicit":false,"imprecise_arg_kinds":false,"is_bound":false,"is_ellipsis_args":false,"name":"__iter__ of ListFeatureMonitorsPager","ret_type":{".class":"Instance","args":["google.cloud.aiplatform_v1beta1.types.feature_monitor.FeatureMonitor"],"extra_attrs":null,"type_ref":"typing.Iterator"},"type_guard":null,"type_is":null,"unpack_kwargs":false,"variables":[]}}},"__repr__":{".class":"SymbolTableNode","kind":"Mdef","node":{".class":"FuncDef","abstract_status":0,"arg_kinds":[0],"arg_names":[null],"dataclass_transform_spec":null,"deprecated":null,"flags":["is_trivial_self"],"fullname":"google.cloud.aiplatform_v1beta1.services.feature_registry_service.pagers.ListFeatureMonitorsPager.__repr__","name":"__repr__","original_first_arg":"self","type":{".class":"CallableType","arg_kinds":[0],"arg_names":[null],"arg_types":["google.cloud.aiplatform_v1beta1.services.feature_registry_service.pagers.ListFeatureMonitorsPager"],"fallback":"builtins.function","from_concatenate":false,"implicit":false,"imprecise_arg_kinds":false,"is_bound":false,"is_ellipsis_args":false,"name":"__repr__ of ListFeatureMonitorsPager","ret_type":"builtins.str","type_guard":null,"type_is":null,"unpack_kwargs":false,"variables":[]}}},"_metadata":{".class":"SymbolTableNode","implicit":true,"kind":"Mdef","node":{".class":"Var","flags":["is_ready","is_inferred"],"fullname":"google.cloud.aiplatform_v1beta1.services.feature_registry_service.pagers.ListFeatureMonitorsPager._metadata","name":"_metadata","setter_type":null,"type":{".class":"Instance","args":[{".class":"TupleType","implicit":false,"items":["builtins.str",{".class":"UnionType","items":["builtins.str","builtins.bytes"],"uses_pep604_syntax":false}],"partial_fallback":{".class":"Instance","args":[{".class":"AnyType","missing_import_name":null,"source_any":null,"type_of_any":6}],"extra_attrs":null,"type_ref":"builtins.tuple"}}],"extra_attrs":null,"type_ref":"typing.Sequence"}}},"_method":{".class":"SymbolTableNode","implicit":true,"kind":"Mdef","node":{".class":"Var","flags":["is_ready","is_inferred"],"fullname":"google.cloud.aiplatform_v1beta1.services.feature_registry_service.pagers.ListFeatureMonitorsPager._method","name":"_method","setter_type":null,"type":{".class":"CallableType","arg_kinds":[2,4],"arg_names":[null,null],"arg_types":[{".class":"AnyType","missing_import_name":null,"source_any":null,"type_of_any":2},{".class":"AnyType","missing_import_name":null,"source_any":null,"type_of_any":2}],"fallback":"builtins.function","from_concatenate":false,"implicit":false,"imprecise_arg_kinds":false,"is_bound":false,"is_ellipsis_args":true,"name":null,"ret_type":"google.cloud.aiplatform_v1beta1.types.feature_registry_service.ListFeatureMonitorsResponse","type_guard":null,"type_is":null,"unpack_kwargs":false,"variables":[]}}},"_request":{".class":"SymbolTableNode","implicit":true,"kind":"Mdef","node":{".class":"Var","flags":["is_ready","is_inferred"],"fullname":"google.cloud.aiplatform_v1beta1.services.feature_registry_service.pagers.ListFeatureMonitorsPager._request","name":"_request","setter_type":null,"type":"google.cloud.aiplatform_v1beta1.types.feature_registry_service.ListFeatureMonitorsRequest"}},"_response":{".class":"SymbolTableNode","implicit":true,"kind":"Mdef","node":{".class":"Var","flags":["is_ready","is_inferred"],"fullname":"google.cloud.aiplatform_v1beta1.services.feature_registry_service.pagers.ListFeatureMonitorsPager._response","name":"_response","setter_type":null,"type":"google.cloud.aiplatform_v1beta1.types.feature_registry_service.ListFeatureMonitorsResponse"}},"_retry":{".class":"SymbolTableNode","implicit":true,"kind":"Mdef","node":{".class":"Var","flags":["is_ready","is_inferred"],"fullname":"google.cloud.aiplatform_v1beta1.services.feature_registry_service.pagers.ListFeatureMonitorsPager._retry","name":"_retry","setter_type":null,"type":{".class":"TypeAliasType","args":[],"type_ref":"google.cloud.aiplatform_v1beta1.services.feature_registry_service.pagers.OptionalRetry"}}},"_timeout":{".class":"SymbolTableNode","implicit":true,"kind":"Mdef","node":{".class":"Var","flags":["is_ready","is_inferred"],"fullname":"google.cloud.aiplatform_v1beta1.services.feature_registry_service.pagers.ListFeatureMonitorsPager._timeout","name":"_timeout","setter_type":null,"type":{".class":"UnionType","items":["builtins.float","builtins.object"],"uses_pep604_syntax":false}}},"pages":{".class":"SymbolTableNode","kind":"Mdef","node":{".class":"Decorator","func":{".class":"FuncDef","abstract_status":0,"arg_kinds":[0],"arg_names":["self"],"dataclass_transform_spec":null,"deprecated":null,"flags":["is_property","is_generator","is_decorated","is_trivial_self"],"fullname":"google.cloud.aiplatform_v1beta1.services.feature_registry_service.pagers.ListFeatureMonitorsPager.pages","name":"pages","original_first_arg":"self","type":{".class":"CallableType","arg_kinds":[0],"arg_names":["self"],"arg_types":["google.cloud.aiplatform_v1beta1.services.feature_registry_service.pagers.ListFeatureMonitorsPager"],"fallback":"builtins.function","from_concatenate":false,"implicit":false,"imprecise_arg_kinds":false,"is_bound":false,"is_ellipsis_args":false,"name":"pages of ListFeatureMonitorsPager","ret_type":{".class":"Instance","args":["google.cloud.aiplatform_v1beta1.types.feature_registry_service.ListFeatureMonitorsResponse"],"extra_attrs":null,"type_ref":"typing.Iterator"},"type_guard":null,"type_is":null,"unpack_kwargs":false,"variables":[]}},"is_overload":false,"var":{".class":"Var","flags":["is_initialized_in_class","is_property","is_ready","is_inferred"],"fullname":"google.cloud.aiplatform_v1beta1.services.feature_registry_service.pagers.ListFeatureMonitorsPager.pages","name":"pages","setter_type":null,"type":{".class":"CallableType","arg_kinds":[0],"arg_names":["self"],"arg_types":["google.cloud.aiplatform_v1beta1.services.feature_registry_service.pagers.ListFeatureMonitorsPager"],"fallback":"builtins.function","from_concatenate":false,"implicit":false,"imprecise_arg_kinds":false,"is_bound":false,"is_ellipsis_args":false,"name":"pages of ListFeatureMonitorsPager","ret_type":{".class":"Instance","args":["google.cloud.aiplatform_v1beta1.types.feature_registry_service.ListFeatureMonitorsResponse"],"extra_attrs":null,"type_ref":"typing.Iterator"},"type_guard":null,"type_is":null,"unpack_kwargs":false,"variables":[]}}}}},"self_type":{".class":"TypeVarType","default":{".class":"AnyType","missing_import_name":null,"source_any":null,"type_of_any":4},"fullname":"google.cloud.aiplatform_v1beta1.services.feature_registry_service.pagers.ListFeatureMonitorsPager.Self","id":0,"name":"Self","namespace":"","upper_bound":"google.cloud.aiplatform_v1beta1.services.feature_registry_service.pagers.ListFeatureMonitorsPager","values":[],"variance":0},"slots":null,"tuple_type":null,"type_vars":[],"typeddict_type":null}},"ListFeaturesAsyncPager":{".class":"SymbolTableNode","kind":"Gdef","node":{".class":"TypeInfo","_promote":[],"abstract_attributes":[],"alt_promote":null,"bases":["builtins.object"],"dataclass_transform_spec":null,"declared_metaclass":null,"defn":{".class":"ClassDef","fullname":"google.cloud.aiplatform_v1beta1.services.feature_registry_service.pagers.ListFeaturesAsyncPager","name":"ListFeaturesAsyncPager","type_vars":[]},"deletable_attributes":[],"deprecated":null,"flags":[],"fullname":"google.cloud.aiplatform_v1beta1.services.feature_registry_service.pagers.ListFeaturesAsyncPager","has_param_spec_type":false,"metaclass_type":null,"metadata":{},"module_name":"google.cloud.aiplatform_v1beta1.services.feature_registry_service.pagers","mro":["google.cloud.aiplatform_v1beta1.services.feature_registry_service.pagers.ListFeaturesAsyncPager","builtins.object"],"names":{".class":"SymbolTable","__aiter__":{".class":"SymbolTableNode","kind":"Mdef","node":{".class":"FuncDef","abstract_status":0,"arg_kinds":[0],"arg_names":["self"],"dataclass_transform_spec":null,"deprecated":null,"flags":["is_trivial_self"],"fullname":"google.cloud.aiplatform_v1beta1.services.feature_registry_service.pagers.ListFeaturesAsyncPager.__aiter__","name":"__aiter__","original_first_arg":"self","type":{".class":"CallableType","arg_kinds":[0],"arg_names":["self"],"arg_types":["google.cloud.aiplatform_v1beta1.services.feature_registry_service.pagers.ListFeaturesAsyncPager"],"fallback":"builtins.function","from_concatenate":false,"implicit":false,"imprecise_arg_kinds":false,"is_bound":false,"is_ellipsis_args":false,"name":"__aiter__ of ListFeaturesAsyncPager","ret_type":{".class":"Instance","args":["google.cloud.aiplatform_v1beta1.types.feature.Feature"],"extra_attrs":null,"type_ref":"typing.AsyncIterator"},"type_guard":null,"type_is":null,"unpack_kwargs":false,"variables":[]}}},"__getattr__":{".class":"SymbolTableNode","kind":"Mdef","node":{".class":"FuncDef","abstract_status":0,"arg_kinds":[0,0],"arg_names":[null,null],"dataclass_transform_spec":null,"deprecated":null,"flags":["is_trivial_self"],"fullname":"google.cloud.aiplatform_v1beta1.services.feature_registry_service.pagers.ListFeaturesAsyncPager.__getattr__","name":"__getattr__","original_first_arg":"self","type":{".class":"CallableType","arg_kinds":[0,0],"arg_names":[null,null],"arg_types":["google.cloud.aiplatform_v1beta1.services.feature_registry_service.pagers.ListFeaturesAsyncPager","builtins.str"],"fallback":"builtins.function","from_concatenate":false,"implicit":false,"imprecise_arg_kinds":false,"is_bound":false,"is_ellipsis_args":false,"name":"__getattr__ of ListFeaturesAsyncPager","ret_type":{".class":"AnyType","missing_import_name":null,"source_any":null,"type_of_any":2},"type_guard":null,"type_is":null,"unpack_kwargs":false,"variables":[]}}},"__init__":{".class":"SymbolTableNode","kind":"Mdef","node":{".class":"FuncDef","abstract_status":0,"arg_kinds":[0,0,0,0,5,5,5],"arg_names":["self","method","request","response","retry","timeout","metadata"],"dataclass_transform_spec":null,"deprecated":null,"flags":["is_trivial_self"],"fullname":"google.cloud.aiplatform_v1beta1.services.feature_registry_service.pagers.ListFeaturesAsyncPager.__init__","name":"__init__","original_first_arg":"self","type":{".class":"CallableType","arg_kinds":[0,0,0,0,5,5,5],"arg_names":["self","method","request","response","retry","timeout","metadata"],"arg_types":["google.cloud.aiplatform_v1beta1.services.feature_registry_service.pagers.ListFeaturesAsyncPager",{".class":"CallableType","arg_kinds":[2,4],"arg_names":[null,null],"arg_types":[{".class":"AnyType","missing_import_name":null,"source_any":null,"type_of_any":2},{".class":"AnyType","missing_import_name":null,"source_any":null,"type_of_any":2}],"fallback":"builtins.function","from_concatenate":false,"implicit":false,"imprecise_arg_kinds":false,"is_bound":false,"is_ellipsis_args":true,"name":null,"ret_type":{".class":"Instance","args":["google.cloud.aiplatform_v1beta1.types.featurestore_service.ListFeaturesResponse"],"extra_attrs":null,"type_ref":"typing.Awaitable"},"type_guard":null,"type_is":null,"unpack_kwargs":false,"variables":[]},"google.cloud.aiplatform_v1beta1.types.featurestore_service.ListFeaturesRequest","google.cloud.aiplatform_v1beta1.types.featurestore_service.ListFeaturesResponse",{".class":"TypeAliasType","args":[],"type_ref":"google.cloud.aiplatform_v1beta1.services.feature_registry_service.pagers.OptionalAsyncRetry"},{".class":"UnionType","items":["builtins.float","builtins.object"],"uses_pep604_syntax":false},{".class":"Instance","args":[{".class":"TupleType","implicit":false,"items":["builtins.str",{".class":"UnionType","items":["builtins.str","builtins.bytes"],"uses_pep604_syntax":false}],"partial_fallback":{".class":"Instance","args":[{".class":"AnyType","missing_import_name":null,"source_any":null,"type_of_any":6}],"extra_attrs":null,"type_ref":"builtins.tuple"}}],"extra_attrs":null,"type_ref":"typing.Sequence"}],"fallback":"builtins.function","from_concatenate":false,"implicit":false,"imprecise_arg_kinds":false,"is_bound":false,"is_ellipsis_args":false,"name":"__init__ of ListFeaturesAsyncPager","ret_type":{".class":"NoneType"},"type_guard":null,"type_is":null,"unpack_kwargs":false,"variables":[]}}},"__repr__":{".class":"SymbolTableNode","kind":"Mdef","node":{".class":"FuncDef","abstract_status":0,"arg_kinds":[0],"arg_names":[null],"dataclass_transform_spec":null,"deprecated":null,"flags":["is_trivial_self"],"fullname":"google.cloud.aiplatform_v1beta1.services.feature_registry_service.pagers.ListFeaturesAsyncPager.__repr__","name":"__repr__","original_first_arg":"self","type":{".class":"CallableType","arg_kinds":[0],"arg_names":[null],"arg_types":["google.cloud.aiplatform_v1beta1.services.feature_registry_service.pagers.ListFeaturesAsyncPager"],"fallback":"builtins.function","from_concatenate":false,"implicit":false,"imprecise_arg_kinds":false,"is_bound":false,"is_ellipsis_args":false,"name":"__repr__ of ListFeaturesAsyncPager","ret_type":"builtins.str","type_guard":null,"type_is":null,"unpack_kwargs":false,"variables":[]}}},"_metadata":{".class":"SymbolTableNode","implicit":true,"kind":"Mdef","node":{".class":"Var","flags":["is_ready","is_inferred"],"fullname":"google.cloud.aiplatform_v1beta1.services.feature_registry_service.pagers.ListFeaturesAsyncPager._metadata","name":"_metadata","setter_type":null,"type":{".class":"Instance","args":[{".class":"TupleType","implicit":false,"items":["builtins.str",{".class":"UnionType","items":["builtins.str","builtins.bytes"],"uses_pep604_syntax":false}],"partial_fallback":{".class":"Instance","args":[{".class":"AnyType","missing_import_name":null,"source_any":null,"type_of_any":6}],"extra_attrs":null,"type_ref":"builtins.tuple"}}],"extra_attrs":null,"type_ref":"typing.Sequence"}}},"_method":{".class":"SymbolTableNode","implicit":true,"kind":"Mdef","node":{".class":"Var","flags":["is_ready","is_inferred"],"fullname":"google.cloud.aiplatform_v1beta1.services.feature_registry_service.pagers.ListFeaturesAsyncPager._method","name":"_method","setter_type":null,"type":{".class":"CallableType","arg_kinds":[2,4],"arg_names":[null,null],"arg_types":[{".class":"AnyType","missing_import_name":null,"source_any":null,"type_of_any":2},{".class":"AnyType","missing_import_name":null,"source_any":null,"type_of_any":2}],"fallback":"builtins.function","from_concatenate":false,"implicit":false,"imprecise_arg_kinds":false,"is_bound":false,"is_ellipsis_args":true,"name":null,"ret_type":{".class":"Instance","args":["google.cloud.aiplatform_v1beta1.types.featurestore_service.ListFeaturesResponse"],"extra_attrs":null,"type_ref":"typing.Awaitable"},"type_guard":null,"type_is":null,"unpack_kwargs":false,"variables":[]}}},"_request":{".class":"SymbolTableNode","implicit":true,"kind":"Mdef","node":{".class":"Var","flags":["is_ready","is_inferred"],"fullname":"google.cloud.aiplatform_v1beta1.services.feature_registry_service.pagers.ListFeaturesAsyncPager._request","name":"_request","setter_type":null,"type":"google.cloud.aiplatform_v1beta1.types.featurestore_service.ListFeaturesRequest"}},"_response":{".class":"SymbolTableNode","implicit":true,"kind":"Mdef","node":{".class":"Var","flags":["is_ready","is_inferred"],"fullname":"google.cloud.aiplatform_v1beta1.services.feature_registry_service.pagers.ListFeaturesAsyncPager._response","name":"_response","setter_type":null,"type":"google.cloud.aiplatform_v1beta1.types.featurestore_service.ListFeaturesResponse"}},"_retry":{".class":"SymbolTableNode","implicit":true,"kind":"Mdef","node":{".class":"Var","flags":["is_ready","is_inferred"],"fullname":"google.cloud.aiplatform_v1beta1.services.feature_registry_service.pagers.ListFeaturesAsyncPager._retry","name":"_retry","setter_type":null,"type":{".class":"TypeAliasType","args":[],"type_ref":"google.cloud.aiplatform_v1beta1.services.feature_registry_service.pagers.OptionalAsyncRetry"}}},"_timeout":{".class":"SymbolTableNode","implicit":true,"kind":"Mdef","node":{".class":"Var","flags":["is_ready","is_inferred"],"fullname":"google.cloud.aiplatform_v1beta1.services.feature_registry_service.pagers.ListFeaturesAsyncPager._timeout","name":"_timeout","setter_type":null,"type":{".class":"UnionType","items":["builtins.float","builtins.object"],"uses_pep604_syntax":false}}},"pages":{".class":"SymbolTableNode","kind":"Mdef","node":{".class":"Decorator","func":{".class":"FuncDef","abstract_status":0,"arg_kinds":[0],"arg_names":["self"],"dataclass_transform_spec":null,"deprecated":null,"flags":["is_property","is_generator","is_coroutine","is_async_generator","is_decorated","is_trivial_self"],"fullname":"google.cloud.aiplatform_v1beta1.services.feature_registry_service.pagers.ListFeaturesAsyncPager.pages","name":"pages","original_first_arg":"self","type":{".class":"CallableType","arg_kinds":[0],"arg_names":["self"],"arg_types":["google.cloud.aiplatform_v1beta1.services.feature_registry_service.pagers.ListFeaturesAsyncPager"],"fallback":"builtins.function","from_concatenate":false,"implicit":false,"imprecise_arg_kinds":false,"is_bound":false,"is_ellipsis_args":false,"name":"pages of ListFeaturesAsyncPager","ret_type":{".class":"Instance","args":["google.cloud.aiplatform_v1beta1.types.featurestore_service.ListFeaturesResponse"],"extra_attrs":null,"type_ref":"typing.AsyncIterator"},"type_guard":null,"type_is":null,"unpack_kwargs":false,"variables":[]}},"is_overload":false,"var":{".class":"Var","flags":["is_initialized_in_class","is_property","is_ready","is_inferred"],"fullname":"google.cloud.aiplatform_v1beta1.services.feature_registry_service.pagers.ListFeaturesAsyncPager.pages","name":"pages","setter_type":null,"type":{".class":"CallableType","arg_kinds":[0],"arg_names":["self"],"arg_types":["google.cloud.aiplatform_v1beta1.services.feature_registry_service.pagers.ListFeaturesAsyncPager"],"fallback":"builtins.function","from_concatenate":false,"implicit":false,"imprecise_arg_kinds":false,"is_bound":false,"is_ellipsis_args":false,"name":"pages of ListFeaturesAsyncPager","ret_type":{".class":"Instance","args":["google.cloud.aiplatform_v1beta1.types.featurestore_service.ListFeaturesResponse"],"extra_attrs":null,"type_ref":"typing.AsyncIterator"},"type_guard":null,"type_is":null,"unpack_kwargs":false,"variables":[]}}}}},"self_type":{".class":"TypeVarType","default":{".class":"AnyType","missing_import_name":null,"source_any":null,"type_of_any":4},"fullname":"google.cloud.aiplatform_v1beta1.services.feature_registry_service.pagers.ListFeaturesAsyncPager.Self","id":0,"name":"Self","namespace":"","upper_bound":"google.cloud.aiplatform_v1beta1.services.feature_registry_service.pagers.ListFeaturesAsyncPager","values":[],"variance":0},"slots":null,"tuple_type":null,"type_vars":[],"typeddict_type":null}},"ListFeaturesPager":{".class":"SymbolTableNode","kind":"Gdef","node":{".class":"TypeInfo","_promote":[],"abstract_attributes":[],"alt_promote":null,"bases":["builtins.object"],"dataclass_transform_spec":null,"declared_metaclass":null,"defn":{".class":"ClassDef","fullname":"google.cloud.aiplatform_v1beta1.services.feature_registry_service.pagers.ListFeaturesPager","name":"ListFeaturesPager","type_vars":[]},"deletable_attributes":[],"deprecated":null,"flags":[],"fullname":"google.cloud.aiplatform_v1beta1.services.feature_registry_service.pagers.ListFeaturesPager","has_param_spec_type":false,"metaclass_type":null,"metadata":{},"module_name":"google.cloud.aiplatform_v1beta1.services.feature_registry_service.pagers","mro":["google.cloud.aiplatform_v1beta1.services.feature_registry_service.pagers.ListFeaturesPager","builtins.object"],"names":{".class":"SymbolTable","__getattr__":{".class":"SymbolTableNode","kind":"Mdef","node":{".class":"FuncDef","abstract_status":0,"arg_kinds":[0,0],"arg_names":[null,null],"dataclass_transform_spec":null,"deprecated":null,"flags":["is_trivial_self"],"fullname":"google.cloud.aiplatform_v1beta1.services.feature_registry_service.pagers.ListFeaturesPager.__getattr__","name":"__getattr__","original_first_arg":"self","type":{".class":"CallableType","arg_kinds":[0,0],"arg_names":[null,null],"arg_types":["google.cloud.aiplatform_v1beta1.services.feature_registry_service.pagers.ListFeaturesPager","builtins.str"],"fallback":"builtins.function","from_concatenate":false,"implicit":false,"imprecise_arg_kinds":false,"is_bound":false,"is_ellipsis_args":false,"name":"__getattr__ of ListFeaturesPager","ret_type":{".class":"AnyType","missing_import_name":null,"source_any":null,"type_of_any":2},"type_guard":null,"type_is":null,"unpack_kwargs":false,"variables":[]}}},"__init__":{".class":"SymbolTableNode","kind":"Mdef","node":{".class":"FuncDef","abstract_status":0,"arg_kinds":[0,0,0,0,5,5,5],"arg_names":["self","method","request","response","retry","timeout","metadata"],"dataclass_transform_spec":null,"deprecated":null,"flags":["is_trivial_self"],"fullname":"google.cloud.aiplatform_v1beta1.services.feature_registry_service.pagers.ListFeaturesPager.__init__","name":"__init__","original_first_arg":"self","type":{".class":"CallableType","arg_kinds":[0,0,0,0,5,5,5],"arg_names":["self","method","request","response","retry","timeout","metadata"],"arg_types":["google.cloud.aiplatform_v1beta1.services.feature_registry_service.pagers.ListFeaturesPager",{".class":"CallableType","arg_kinds":[2,4],"arg_names":[null,null],"arg_types":[{".class":"AnyType","missing_import_name":null,"source_any":null,"type_of_any":2},{".class":"AnyType","missing_import_name":null,"source_any":null,"type_of_any":2}],"fallback":"builtins.function","from_concatenate":false,"implicit":false,"imprecise_arg_kinds":false,"is_bound":false,"is_ellipsis_args":true,"name":null,"ret_type":"google.cloud.aiplatform_v1beta1.types.featurestore_service.ListFeaturesResponse","type_guard":null,"type_is":null,"unpack_kwargs":false,"variables":[]},"google.cloud.aiplatform_v1beta1.types.featurestore_service.ListFeaturesRequest","google.cloud.aiplatform_v1beta1.types.featurestore_service.ListFeaturesResponse",{".class":"TypeAliasType","args":[],"type_ref":"google.cloud.aiplatform_v1beta1.services.feature_registry_service.pagers.OptionalRetry"},{".class":"UnionType","items":["builtins.float","builtins.object"],"uses_pep604_syntax":false},{".class":"Instance","args":[{".class":"TupleType","implicit":false,"items":["builtins.str",{".class":"UnionType","items":["builtins.str","builtins.bytes"],"uses_pep604_syntax":false}],"partial_fallback":{".class":"Instance","args":[{".class":"AnyType","missing_import_name":null,"source_any":null,"type_of_any":6}],"extra_attrs":null,"type_ref":"builtins.tuple"}}],"extra_attrs":null,"type_ref":"typing.Sequence"}],"fallback":"builtins.function","from_concatenate":false,"implicit":false,"imprecise_arg_kinds":false,"is_bound":false,"is_ellipsis_args":false,"name":"__init__ of ListFeaturesPager","ret_type":{".class":"NoneType"},"type_guard":null,"type_is":null,"unpack_kwargs":false,"variables":[]}}},"__iter__":{".class":"SymbolTableNode","kind":"Mdef","node":{".class":"FuncDef","abstract_status":0,"arg_kinds":[0],"arg_names":[null],"dataclass_transform_spec":null,"deprecated":null,"flags":["is_trivial_self"],"fullname":"google.cloud.aiplatform_v1beta1.services.feature_registry_service.pagers.ListFeaturesPager.__iter__","name":"__iter__","original_first_arg":"self","type":{".class":"CallableType","arg_kinds":[0],"arg_names":[null],"arg_types":["google.cloud.aiplatform_v1beta1.services.feature_registry_service.pagers.ListFeaturesPager"],"fallback":"builtins.function","from_concatenate":false,"implicit":false,"imprecise_arg_kinds":false,"is_bound":false,"is_ellipsis_args":false,"name":"__iter__ of ListFeaturesPager","ret_type":{".class":"Instance","args":["google.cloud.aiplatform_v1beta1.types.feature.Feature"],"extra_attrs":null,"type_ref":"typing.Iterator"},"type_guard":null,"type_is":null,"unpack_kwargs":false,"variables":[]}}},"__repr__":{".class":"SymbolTableNode","kind":"Mdef","node":{".class":"FuncDef","abstract_status":0,"arg_kinds":[0],"arg_names":[null],"dataclass_transform_spec":null,"deprecated":null,"flags":["is_trivial_self"],"fullname":"google.cloud.aiplatform_v1beta1.services.feature_registry_service.pagers.ListFeaturesPager.__repr__","name":"__repr__","original_first_arg":"self","type":{".class":"CallableType","arg_kinds":[0],"arg_names":[null],"arg_types":["google.cloud.aiplatform_v1beta1.services.feature_registry_service.pagers.ListFeaturesPager"],"fallback":"builtins.function","from_concatenate":false,"implicit":false,"imprecise_arg_kinds":false,"is_bound":false,"is_ellipsis_args":false,"name":"__repr__ of ListFeaturesPager","ret_type":"builtins.str","type_guard":null,"type_is":null,"unpack_kwargs":false,"variables":[]}}},"_metadata":{".class":"SymbolTableNode","implicit":true,"kind":"Mdef","node":{".class":"Var","flags":["is_ready","is_inferred"],"fullname":"google.cloud.aiplatform_v1beta1.services.feature_registry_service.pagers.ListFeaturesPager._metadata","name":"_metadata","setter_type":null,"type":{".class":"Instance","args":[{".class":"TupleType","implicit":false,"items":["builtins.str",{".class":"UnionType","items":["builtins.str","builtins.bytes"],"uses_pep604_syntax":false}],"partial_fallback":{".class":"Instance","args":[{".class":"AnyType","missing_import_name":null,"source_any":null,"type_of_any":6}],"extra_attrs":null,"type_ref":"builtins.tuple"}}],"extra_attrs":null,"type_ref":"typing.Sequence"}}},"_method":{".class":"SymbolTableNode","implicit":true,"kind":"Mdef","node":{".class":"Var","flags":["is_ready","is_inferred"],"fullname":"google.cloud.aiplatform_v1beta1.services.feature_registry_service.pagers.ListFeaturesPager._method","name":"_method","setter_type":null,"type":{".class":"CallableType","arg_kinds":[2,4],"arg_names":[null,null],"arg_types":[{".class":"AnyType","missing_import_name":null,"source_any":null,"type_of_any":2},{".class":"AnyType","missing_import_name":null,"source_any":null,"type_of_any":2}],"fallback":"builtins.function","from_concatenate":false,"implicit":false,"imprecise_arg_kinds":false,"is_bound":false,"is_ellipsis_args":true,"name":null,"ret_type":"google.cloud.aiplatform_v1beta1.types.featurestore_service.ListFeaturesResponse","type_guard":null,"type_is":null,"unpack_kwargs":false,"variables":[]}}},"_request":{".class":"SymbolTableNode","implicit":true,"kind":"Mdef","node":{".class":"Var","flags":["is_ready","is_inferred"],"fullname":"google.cloud.aiplatform_v1beta1.services.feature_registry_service.pagers.ListFeaturesPager._request","name":"_request","setter_type":null,"type":"google.cloud.aiplatform_v1beta1.types.featurestore_service.ListFeaturesRequest"}},"_response":{".class":"SymbolTableNode","implicit":true,"kind":"Mdef","node":{".class":"Var","flags":["is_ready","is_inferred"],"fullname":"google.cloud.aiplatform_v1beta1.services.feature_registry_service.pagers.ListFeaturesPager._response","name":"_response","setter_type":null,"type":"google.cloud.aiplatform_v1beta1.types.featurestore_service.ListFeaturesResponse"}},"_retry":{".class":"SymbolTableNode","implicit":true,"kind":"Mdef","node":{".class":"Var","flags":["is_ready","is_inferred"],"fullname":"google.cloud.aiplatform_v1beta1.services.feature_registry_service.pagers.ListFeaturesPager._retry","name":"_retry","setter_type":null,"type":{".class":"TypeAliasType","args":[],"type_ref":"google.cloud.aiplatform_v1beta1.services.feature_registry_service.pagers.OptionalRetry"}}},"_timeout":{".class":"SymbolTableNode","implicit":true,"kind":"Mdef","node":{".class":"Var","flags":["is_ready","is_inferred"],"fullname":"google.cloud.aiplatform_v1beta1.services.feature_registry_service.pagers.ListFeaturesPager._timeout","name":"_timeout","setter_type":null,"type":{".class":"UnionType","items":["builtins.float","builtins.object"],"uses_pep604_syntax":false}}},"pages":{".class":"SymbolTableNode","kind":"Mdef","node":{".class":"Decorator","func":{".class":"FuncDef","abstract_status":0,"arg_kinds":[0],"arg_names":["self"],"dataclass_transform_spec":null,"deprecated":null,"flags":["is_property","is_generator","is_decorated","is_trivial_self"],"fullname":"google.cloud.aiplatform_v1beta1.services.feature_registry_service.pagers.ListFeaturesPager.pages","name":"pages","original_first_arg":"self","type":{".class":"CallableType","arg_kinds":[0],"arg_names":["self"],"arg_types":["google.cloud.aiplatform_v1beta1.services.feature_registry_service.pagers.ListFeaturesPager"],"fallback":"builtins.function","from_concatenate":false,"implicit":false,"imprecise_arg_kinds":false,"is_bound":false,"is_ellipsis_args":false,"name":"pages of ListFeaturesPager","ret_type":{".class":"Instance","args":["google.cloud.aiplatform_v1beta1.types.featurestore_service.ListFeaturesResponse"],"extra_attrs":null,"type_ref":"typing.Iterator"},"type_guard":null,"type_is":null,"unpack_kwargs":false,"variables":[]}},"is_overload":false,"var":{".class":"Var","flags":["is_initialized_in_class","is_property","is_ready","is_inferred"],"fullname":"google.cloud.aiplatform_v1beta1.services.feature_registry_service.pagers.ListFeaturesPager.pages","name":"pages","setter_type":null,"type":{".class":"CallableType","arg_kinds":[0],"arg_names":["self"],"arg_types":["google.cloud.aiplatform_v1beta1.services.feature_registry_service.pagers.ListFeaturesPager"],"fallback":"builtins.function","from_concatenate":false,"implicit":false,"imprecise_arg_kinds":false,"is_bound":false,"is_ellipsis_args":false,"name":"pages of ListFeaturesPager","ret_type":{".class":"Instance","args":["google.cloud.aiplatform_v1beta1.types.featurestore_service.ListFeaturesResponse"],"extra_attrs":null,"type_ref":"typing.Iterator"},"type_guard":null,"type_is":null,"unpack_kwargs":false,"variables":[]}}}}},"self_type":{".class":"TypeVarType","default":{".class":"AnyType","missing_import_name":null,"source_any":null,"type_of_any":4},"fullname":"google.cloud.aiplatform_v1beta1.services.feature_registry_service.pagers.ListFeaturesPager.Self","id":0,"name":"Self","namespace":"","upper_bound":"google.cloud.aiplatform_v1beta1.services.feature_registry_service.pagers.ListFeaturesPager","values":[],"variance":0},"slots":null,"tuple_type":null,"type_vars":[],"typeddict_type":null}},"Optional":{".class":"SymbolTableNode","cross_ref":"typing.Optional","kind":"Gdef"},"OptionalAsyncRetry":{".class":"SymbolTableNode","kind":"Gdef","node":{".class":"TypeAlias","alias_tvars":[],"fullname":"google.cloud.aiplatform_v1beta1.services.feature_registry_service.pagers.OptionalAsyncRetry","module":"google.cloud.aiplatform_v1beta1.services.feature_registry_service.pagers","no_args":false,"normalized":false,"python_3_12_type_alias":false,"target":{".class":"UnionType","items":["google.api_core.retry.retry_unary_async.AsyncRetry","google.api_core.gapic_v1.method._MethodDefault",{".class":"NoneType"}],"uses_pep604_syntax":false}}},"OptionalRetry":{".class":"SymbolTableNode","kind":"Gdef","node":{".class":"TypeAlias","alias_tvars":[],"fullname":"google.cloud.aiplatform_v1beta1.services.feature_registry_service.pagers.OptionalRetry","module":"google.cloud.aiplatform_v1beta1.services.feature_registry_service.pagers","no_args":false,"normalized":false,"python_3_12_type_alias":false,"target":{".class":"UnionType","items":["google.api_core.retry.retry_unary.Retry","google.api_core.gapic_v1.method._MethodDefault",{".class":"NoneType"}],"uses_pep604_syntax":false}}},"Sequence":{".class":"SymbolTableNode","cross_ref":"typing.Sequence","kind":"Gdef"},"Tuple":{".class":"SymbolTableNode","cross_ref":"typing.Tuple","kind":"Gdef"},"Union":{".class":"SymbolTableNode","cross_ref":"typing.Union","kind":"Gdef"},"__annotations__":{".class":"SymbolTableNode","kind":"Gdef","node":{".class":"Var","flags":["is_ready"],"fullname":"google.cloud.aiplatform_v1beta1.services.feature_registry_service.pagers.__annotations__","name":"__annotations__","setter_type":null,"type":{".class":"Instance","args":["builtins.str",{".class":"AnyType","missing_import_name":null,"source_any":null,"type_of_any":6}],"extra_attrs":null,"type_ref":"builtins.dict"}}},"__doc__":{".class":"SymbolTableNode","kind":"Gdef","node":{".class":"Var","flags":["is_ready"],"fullname":"google.cloud.aiplatform_v1beta1.services.feature_registry_service.pagers.__doc__","name":"__doc__","setter_type":null,"type":"builtins.str"}},"__file__":{".class":"SymbolTableNode","kind":"Gdef","node":{".class":"Var","flags":["is_ready"],"fullname":"google.cloud.aiplatform_v1beta1.services.feature_registry_service.pagers.__file__","name":"__file__","setter_type":null,"type":"builtins.str"}},"__name__":{".class":"SymbolTableNode","kind":"Gdef","node":{".class":"Var","flags":["is_ready"],"fullname":"google.cloud.aiplatform_v1beta1.services.feature_registry_service.pagers.__name__","name":"__name__","setter_type":null,"type":"builtins.str"}},"__package__":{".class":"SymbolTableNode","kind":"Gdef","node":{".class":"Var","flags":["is_ready"],"fullname":"google.cloud.aiplatform_v1beta1.services.feature_registry_service.pagers.__package__","name":"__package__","setter_type":null,"type":"builtins.str"}},"__spec__":{".class":"SymbolTableNode","kind":"Gdef","node":{".class":"Var","flags":["is_ready"],"fullname":"google.cloud.aiplatform_v1beta1.services.feature_registry_service.pagers.__spec__","name":"__spec__","setter_type":null,"type":"_frozen_importlib.ModuleSpec"}},"feature":{".class":"SymbolTableNode","cross_ref":"google.cloud.aiplatform_v1beta1.types.feature","kind":"Gdef"},"feature_group":{".class":"SymbolTableNode","cross_ref":"google.cloud.aiplatform_v1beta1.types.feature_group","kind":"Gdef"},"feature_monitor":{".class":"SymbolTableNode","cross_ref":"google.cloud.aiplatform_v1beta1.types.feature_monitor","kind":"Gdef"},"feature_monitor_job":{".class":"SymbolTableNode","cross_ref":"google.cloud.aiplatform_v1beta1.types.feature_monitor_job","kind":"Gdef"},"feature_registry_service":{".class":"SymbolTableNode","cross_ref":"google.cloud.aiplatform_v1beta1.types.feature_registry_service","kind":"Gdef"},"featurestore_service":{".class":"SymbolTableNode","cross_ref":"google.cloud.aiplatform_v1beta1.types.featurestore_service","kind":"Gdef"},"gapic_v1":{".class":"SymbolTableNode","cross_ref":"google.api_core.gapic_v1","kind":"Gdef"},"retries":{".class":"SymbolTableNode","cross_ref":"google.api_core.retry","kind":"Gdef"},"retries_async":{".class":"SymbolTableNode","cross_ref":"google.api_core.retry_async","kind":"Gdef"}},"path":"/home/tripzydevops/hotel/venv/lib/python3.11/site-packages/google/cloud/aiplatform_v1beta1/services/feature_registry_service/pagers.py"}