{".class":"MypyFile","_fullname":"storage3._sync.bucket","future_import_flags":["annotations"],"is_partial_stub_package":false,"is_stub":false,"names":{".class":"SymbolTable","Any":{".class":"SymbolTableNode","cross_ref":"typing.Any","kind":"Gdef","module_public":false},"Client":{".class":"SymbolTableNode","cross_ref":"httpx._client.Client","kind":"Gdef","module_public":false},"CreateOrUpdateBucketOptions":{".class":"SymbolTableNode","cross_ref":"storage3.types.CreateOrUpdateBucketOptions","kind":"Gdef","module_public":false},"HTTPStatusError":{".class":"SymbolTableNode","cross_ref":"httpx._exceptions.HTTPStatusError","kind":"Gdef","module_public":false},"Headers":{".class":"SymbolTableNode","cross_ref":"httpx._models.Headers","kind":"Gdef","module_public":false},"Optional":{".class":"SymbolTableNode","cross_ref":"typing.Optional","kind":"Gdef","module_public":false},"RequestMethod":{".class":"SymbolTableNode","cross_ref":"storage3.types.RequestMethod","kind":"Gdef","module_public":false},"Response":{".class":"SymbolTableNode","cross_ref":"httpx._models.Response","kind":"Gdef","module_public":false},"StorageApiError":{".class":"SymbolTableNode","cross_ref":"storage3.exceptions.StorageApiError","kind":"Gdef","module_public":false},"SyncBucket":{".class":"SymbolTableNode","cross_ref":"storage3._sync.file_api.SyncBucket","kind":"Gdef","module_public":false},"SyncStorageBucketAPI":{".class":"SymbolTableNode","kind":"Gdef","node":{".class":"TypeInfo","_promote":[],"abstract_attributes":[],"alt_promote":null,"bases":["builtins.object"],"dataclass_transform_spec":null,"declared_metaclass":null,"defn":{".class":"ClassDef","fullname":"storage3._sync.bucket.SyncStorageBucketAPI","name":"SyncStorageBucketAPI","type_vars":[]},"deletable_attributes":[],"deprecated":null,"flags":[],"fullname":"storage3._sync.bucket.SyncStorageBucketAPI","has_param_spec_type":false,"metaclass_type":null,"metadata":{},"module_name":"storage3._sync.bucket","mro":["storage3._sync.bucket.SyncStorageBucketAPI","builtins.object"],"names":{".class":"SymbolTable","__init__":{".class":"SymbolTableNode","kind":"Mdef","node":{".class":"FuncDef","abstract_status":0,"arg_kinds":[0,0,0,0],"arg_names":["self","session","url","headers"],"dataclass_transform_spec":null,"deprecated":null,"flags":["is_trivial_self"],"fullname":"storage3._sync.bucket.SyncStorageBucketAPI.__init__","name":"__init__","original_first_arg":"self","type":{".class":"CallableType","arg_kinds":[0,0,0,0],"arg_names":["self","session","url","headers"],"arg_types":["storage3._sync.bucket.SyncStorageBucketAPI","httpx._client.Client","builtins.str","httpx._models.Headers"],"fallback":"builtins.function","from_concatenate":false,"implicit":false,"imprecise_arg_kinds":false,"is_bound":false,"is_ellipsis_args":false,"name":"__init__ of SyncStorageBucketAPI","ret_type":{".class":"NoneType"},"type_guard":null,"type_is":null,"unpack_kwargs":false,"variables":[]}}},"_base_url":{".class":"SymbolTableNode","implicit":true,"kind":"Mdef","node":{".class":"Var","flags":["is_ready","is_inferred"],"fullname":"storage3._sync.bucket.SyncStorageBucketAPI._base_url","name":"_base_url","setter_type":null,"type":"yarl._url.URL"}},"_client":{".class":"SymbolTableNode","implicit":true,"kind":"Mdef","node":{".class":"Var","flags":["is_ready","is_inferred"],"fullname":"storage3._sync.bucket.SyncStorageBucketAPI._client","name":"_client","setter_type":null,"type":"httpx._client.Client"}},"_headers":{".class":"SymbolTableNode","implicit":true,"kind":"Mdef","node":{".class":"Var","flags":["is_ready","is_inferred"],"fullname":"storage3._sync.bucket.SyncStorageBucketAPI._headers","name":"_headers","setter_type":null,"type":"httpx._models.Headers"}},"_request":{".class":"SymbolTableNode","kind":"Mdef","node":{".class":"FuncDef","abstract_status":0,"arg_kinds":[0,0,0,1],"arg_names":["self","method","path","json"],"dataclass_transform_spec":null,"deprecated":null,"flags":["is_trivial_self"],"fullname":"storage3._sync.bucket.SyncStorageBucketAPI._request","name":"_request","original_first_arg":"self","type":{".class":"CallableType","arg_kinds":[0,0,0,1],"arg_names":["self","method","path","json"],"arg_types":["storage3._sync.bucket.SyncStorageBucketAPI",{".class":"TypeAliasType","args":[],"type_ref":"storage3.types.RequestMethod"},{".class":"Instance","args":["builtins.str"],"extra_attrs":null,"type_ref":"builtins.list"},{".class":"UnionType","items":[{".class":"Instance","args":[{".class":"AnyType","missing_import_name":null,"source_any":null,"type_of_any":2},{".class":"AnyType","missing_import_name":null,"source_any":null,"type_of_any":2}],"extra_attrs":null,"type_ref":"builtins.dict"},{".class":"NoneType"}],"uses_pep604_syntax":false}],"fallback":"builtins.function","from_concatenate":false,"implicit":false,"imprecise_arg_kinds":false,"is_bound":false,"is_ellipsis_args":false,"name":"_request of SyncStorageBucketAPI","ret_type":"httpx._models.Response","type_guard":null,"type_is":null,"unpack_kwargs":false,"variables":[]}}},"create_bucket":{".class":"SymbolTableNode","kind":"Mdef","node":{".class":"FuncDef","abstract_status":0,"arg_kinds":[0,0,1,1],"arg_names":["self","id","name","options"],"dataclass_transform_spec":null,"deprecated":null,"flags":["is_trivial_self"],"fullname":"storage3._sync.bucket.SyncStorageBucketAPI.create_bucket","name":"create_bucket","original_first_arg":"self","type":{".class":"CallableType","arg_kinds":[0,0,1,1],"arg_names":["self","id","name","options"],"arg_types":["storage3._sync.bucket.SyncStorageBucketAPI","builtins.str",{".class":"UnionType","items":["builtins.str",{".class":"NoneType"}],"uses_pep604_syntax":false},{".class":"UnionType","items":[{".class":"TypeAliasType","args":[],"type_ref":"storage3.types.CreateOrUpdateBucketOptions"},{".class":"NoneType"}],"uses_pep604_syntax":false}],"fallback":"builtins.function","from_concatenate":false,"implicit":false,"imprecise_arg_kinds":false,"is_bound":false,"is_ellipsis_args":false,"name":"create_bucket of SyncStorageBucketAPI","ret_type":{".class":"Instance","args":["builtins.str","builtins.str"],"extra_attrs":null,"type_ref":"builtins.dict"},"type_guard":null,"type_is":null,"unpack_kwargs":false,"variables":[]}}},"delete_bucket":{".class":"SymbolTableNode","kind":"Mdef","node":{".class":"FuncDef","abstract_status":0,"arg_kinds":[0,0],"arg_names":["self","id"],"dataclass_transform_spec":null,"deprecated":null,"flags":["is_trivial_self"],"fullname":"storage3._sync.bucket.SyncStorageBucketAPI.delete_bucket","name":"delete_bucket","original_first_arg":"self","type":{".class":"CallableType","arg_kinds":[0,0],"arg_names":["self","id"],"arg_types":["storage3._sync.bucket.SyncStorageBucketAPI","builtins.str"],"fallback":"builtins.function","from_concatenate":false,"implicit":false,"imprecise_arg_kinds":false,"is_bound":false,"is_ellipsis_args":false,"name":"delete_bucket of SyncStorageBucketAPI","ret_type":{".class":"Instance","args":["builtins.str","builtins.str"],"extra_attrs":null,"type_ref":"builtins.dict"},"type_guard":null,"type_is":null,"unpack_kwargs":false,"variables":[]}}},"empty_bucket":{".class":"SymbolTableNode","kind":"Mdef","node":{".class":"FuncDef","abstract_status":0,"arg_kinds":[0,0],"arg_names":["self","id"],"dataclass_transform_spec":null,"deprecated":null,"flags":["is_trivial_self"],"fullname":"storage3._sync.bucket.SyncStorageBucketAPI.empty_bucket","name":"empty_bucket","original_first_arg":"self","type":{".class":"CallableType","arg_kinds":[0,0],"arg_names":["self","id"],"arg_types":["storage3._sync.bucket.SyncStorageBucketAPI","builtins.str"],"fallback":"builtins.function","from_concatenate":false,"implicit":false,"imprecise_arg_kinds":false,"is_bound":false,"is_ellipsis_args":false,"name":"empty_bucket of SyncStorageBucketAPI","ret_type":{".class":"Instance","args":["builtins.str","builtins.str"],"extra_attrs":null,"type_ref":"builtins.dict"},"type_guard":null,"type_is":null,"unpack_kwargs":false,"variables":[]}}},"get_bucket":{".class":"SymbolTableNode","kind":"Mdef","node":{".class":"FuncDef","abstract_status":0,"arg_kinds":[0,0],"arg_names":["self","id"],"dataclass_transform_spec":null,"deprecated":null,"flags":["is_trivial_self"],"fullname":"storage3._sync.bucket.SyncStorageBucketAPI.get_bucket","name":"get_bucket","original_first_arg":"self","type":{".class":"CallableType","arg_kinds":[0,0],"arg_names":["self","id"],"arg_types":["storage3._sync.bucket.SyncStorageBucketAPI","builtins.str"],"fallback":"builtins.function","from_concatenate":false,"implicit":false,"imprecise_arg_kinds":false,"is_bound":false,"is_ellipsis_args":false,"name":"get_bucket of SyncStorageBucketAPI","ret_type":"storage3._sync.file_api.SyncBucket","type_guard":null,"type_is":null,"unpack_kwargs":false,"variables":[]}}},"list_buckets":{".class":"SymbolTableNode","kind":"Mdef","node":{".class":"FuncDef","abstract_status":0,"arg_kinds":[0],"arg_names":["self"],"dataclass_transform_spec":null,"deprecated":null,"flags":["is_trivial_self"],"fullname":"storage3._sync.bucket.SyncStorageBucketAPI.list_buckets","name":"list_buckets","original_first_arg":"self","type":{".class":"CallableType","arg_kinds":[0],"arg_names":["self"],"arg_types":["storage3._sync.bucket.SyncStorageBucketAPI"],"fallback":"builtins.function","from_concatenate":false,"implicit":false,"imprecise_arg_kinds":false,"is_bound":false,"is_ellipsis_args":false,"name":"list_buckets of SyncStorageBucketAPI","ret_type":{".class":"Instance","args":["storage3._sync.file_api.SyncBucket"],"extra_attrs":null,"type_ref":"builtins.list"},"type_guard":null,"type_is":null,"unpack_kwargs":false,"variables":[]}}},"update_bucket":{".class":"SymbolTableNode","kind":"Mdef","node":{".class":"FuncDef","abstract_status":0,"arg_kinds":[0,0,0],"arg_names":["self","id","options"],"dataclass_transform_spec":null,"deprecated":null,"flags":["is_trivial_self"],"fullname":"storage3._sync.bucket.SyncStorageBucketAPI.update_bucket","name":"update_bucket","original_first_arg":"self","type":{".class":"CallableType","arg_kinds":[0,0,0],"arg_names":["self","id","options"],"arg_types":["storage3._sync.bucket.SyncStorageBucketAPI","builtins.str",{".class":"TypeAliasType","args":[],"type_ref":"storage3.types.CreateOrUpdateBucketOptions"}],"fallback":"builtins.function","from_concatenate":false,"implicit":false,"imprecise_arg_kinds":false,"is_bound":false,"is_ellipsis_args":false,"name":"update_bucket of SyncStorageBucketAPI","ret_type":{".class":"Instance","args":["builtins.str","builtins.str"],"extra_attrs":null,"type_ref":"builtins.dict"},"type_guard":null,"type_is":null,"unpack_kwargs":false,"variables":[]}}}},"self_type":{".class":"TypeVarType","default":{".class":"AnyType","missing_import_name":null,"source_any":null,"type_of_any":4},"fullname":"storage3._sync.bucket.SyncStorageBucketAPI.Self","id":0,"name":"Self","namespace":"","upper_bound":"storage3._sync.bucket.SyncStorageBucketAPI","values":[],"variance":0},"slots":null,"tuple_type":null,"type_vars":[],"typeddict_type":null}},"URL":{".class":"SymbolTableNode","cross_ref":"yarl._url.URL","kind":"Gdef","module_public":false},"__all__":{".class":"SymbolTableNode","kind":"Gdef","module_public":false,"node":{".class":"Var","flags":["is_ready","is_inferred","has_explicit_value"],"fullname":"storage3._sync.bucket.__all__","name":"__all__","setter_type":null,"type":{".class":"Instance","args":["builtins.str"],"extra_attrs":null,"type_ref":"builtins.list"}}},"__annotations__":{".class":"SymbolTableNode","kind":"Gdef","module_public":false,"node":{".class":"Var","flags":["is_ready"],"fullname":"storage3._sync.bucket.__annotations__","name":"__annotations__","setter_type":null,"type":{".class":"Instance","args":["builtins.str",{".class":"AnyType","missing_import_name":null,"source_any":null,"type_of_any":6}],"extra_attrs":null,"type_ref":"builtins.dict"}}},"__doc__":{".class":"SymbolTableNode","kind":"Gdef","module_public":false,"node":{".class":"Var","flags":["is_ready"],"fullname":"storage3._sync.bucket.__doc__","name":"__doc__","setter_type":null,"type":"builtins.str"}},"__file__":{".class":"SymbolTableNode","kind":"Gdef","module_public":false,"node":{".class":"Var","flags":["is_ready"],"fullname":"storage3._sync.bucket.__file__","name":"__file__","setter_type":null,"type":"builtins.str"}},"__name__":{".class":"SymbolTableNode","kind":"Gdef","module_public":false,"node":{".class":"Var","flags":["is_ready"],"fullname":"storage3._sync.bucket.__name__","name":"__name__","setter_type":null,"type":"builtins.str"}},"__package__":{".class":"SymbolTableNode","kind":"Gdef","module_public":false,"node":{".class":"Var","flags":["is_ready"],"fullname":"storage3._sync.bucket.__package__","name":"__package__","setter_type":null,"type":"builtins.str"}},"__spec__":{".class":"SymbolTableNode","kind":"Gdef","module_public":false,"node":{".class":"Var","flags":["is_ready"],"fullname":"storage3._sync.bucket.__spec__","name":"__spec__","setter_type":null,"type":"_frozen_importlib.ModuleSpec"}},"annotations":{".class":"SymbolTableNode","cross_ref":"__future__.annotations","kind":"Gdef","module_public":false},"warnings":{".class":"SymbolTableNode","cross_ref":"warnings","kind":"Gdef","module_public":false}},"path":"/home/tripzydevops/hotel/venv/lib/python3.11/site-packages/storage3/_sync/bucket.py"}